{
"meta":{"test_sets":[],"test_metrics":[],"learn_metrics":[{"best_value":"Min","name":"RMSE"}],"launch_mode":"Train","parameters":"","iteration_count":1000,"learn_sets":["learn"],"name":"experiment"},
"iterations":[
{"learn":[14.61268541],"iteration":0,"passed_time":0.1476548794,"remaining_time":147.5072246},
{"learn":[14.23196558],"iteration":1,"passed_time":0.1484499944,"remaining_time":74.07654722},
{"learn":[13.86674177],"iteration":2,"passed_time":0.1492818793,"remaining_time":49.61134455},
{"learn":[13.49946468],"iteration":3,"passed_time":0.1500009849,"remaining_time":37.35024523},
{"learn":[13.16661202],"iteration":4,"passed_time":0.1512460179,"remaining_time":30.09795755},
{"learn":[12.85632158],"iteration":5,"passed_time":0.1534098676,"remaining_time":25.4149014},
{"learn":[12.56784336],"iteration":6,"passed_time":0.1553176719,"remaining_time":22.03292117},
{"learn":[12.31617801],"iteration":7,"passed_time":0.1572523173,"remaining_time":19.49928734},
{"learn":[12.01509946],"iteration":8,"passed_time":0.1592187135,"remaining_time":17.53174945},
{"learn":[11.71512571],"iteration":9,"passed_time":0.1612923972,"remaining_time":15.96794733},
{"learn":[11.43264457],"iteration":10,"passed_time":0.1634147061,"remaining_time":14.69246767},
{"learn":[11.17973129],"iteration":11,"passed_time":0.1653882402,"remaining_time":13.61696511},
{"learn":[10.93746433],"iteration":12,"passed_time":0.1675238704,"remaining_time":12.7189277},
{"learn":[10.69387075],"iteration":13,"passed_time":0.1680754621,"remaining_time":11.83731469},
{"learn":[10.4615922],"iteration":14,"passed_time":0.168687057,"remaining_time":11.07711674},
{"learn":[10.2299235],"iteration":15,"passed_time":0.1691551161,"remaining_time":10.40303964},
{"learn":[10.01419731],"iteration":16,"passed_time":0.1708339436,"remaining_time":9.878221563},
{"learn":[9.795856918],"iteration":17,"passed_time":0.1722884142,"remaining_time":9.399290151},
{"learn":[9.60040151],"iteration":18,"passed_time":0.1728229532,"remaining_time":8.92312195},
{"learn":[9.418664989],"iteration":19,"passed_time":0.1739061973,"remaining_time":8.521403667},
{"learn":[9.249278645],"iteration":20,"passed_time":0.1752373049,"remaining_time":8.169396262},
{"learn":[9.090113396],"iteration":21,"passed_time":0.1766539456,"remaining_time":7.853070853},
{"learn":[8.909548708],"iteration":22,"passed_time":0.1781358172,"remaining_time":7.566899715},
{"learn":[8.740140208],"iteration":23,"passed_time":0.1795778993,"remaining_time":7.302834572},
{"learn":[8.59377682],"iteration":24,"passed_time":0.1808401198,"remaining_time":7.052764671},
{"learn":[8.453885414],"iteration":25,"passed_time":0.1819204166,"remaining_time":6.815018683},
{"learn":[8.317732234],"iteration":26,"passed_time":0.1830268492,"remaining_time":6.595745345},
{"learn":[8.180896085],"iteration":27,"passed_time":0.1841660652,"remaining_time":6.393193406},
{"learn":[8.053220863],"iteration":28,"passed_time":0.1850717238,"remaining_time":6.196711856},
{"learn":[7.924234474],"iteration":29,"passed_time":0.1860252727,"remaining_time":6.014817152},
{"learn":[7.818879511],"iteration":30,"passed_time":0.1868561912,"remaining_time":5.840762879},
{"learn":[7.719346395],"iteration":31,"passed_time":0.1876362596,"remaining_time":5.675996852},
{"learn":[7.624163594],"iteration":32,"passed_time":0.1885578272,"remaining_time":5.525315725},
{"learn":[7.524952543],"iteration":33,"passed_time":0.1893163264,"remaining_time":5.37881092},
{"learn":[7.424464745],"iteration":34,"passed_time":0.1900670324,"remaining_time":5.240419607},
{"learn":[7.327482321],"iteration":35,"passed_time":0.1908539255,"remaining_time":5.110644004},
{"learn":[7.238666841],"iteration":36,"passed_time":0.1914840259,"remaining_time":4.983759916},
{"learn":[7.158842395],"iteration":37,"passed_time":0.1921428598,"remaining_time":4.864248188},
{"learn":[7.074348246],"iteration":38,"passed_time":0.1927682108,"remaining_time":4.750006425},
{"learn":[6.992269093],"iteration":39,"passed_time":0.1933281472,"remaining_time":4.639875533},
{"learn":[6.925219745],"iteration":40,"passed_time":0.1938184072,"remaining_time":4.533459817},
{"learn":[6.86013671],"iteration":41,"passed_time":0.194433421,"remaining_time":4.434933746},
{"learn":[6.786739622],"iteration":42,"passed_time":0.1949906729,"remaining_time":4.339676139},
{"learn":[6.73057926],"iteration":43,"passed_time":0.1954992776,"remaining_time":4.247666123},
{"learn":[6.666356486],"iteration":44,"passed_time":0.1960540958,"remaining_time":4.160703589},
{"learn":[6.606182832],"iteration":45,"passed_time":0.1966169167,"remaining_time":4.077663882},
{"learn":[6.547854615],"iteration":46,"passed_time":0.1971436362,"remaining_time":3.997401815},
{"learn":[6.49240675],"iteration":47,"passed_time":0.1976677328,"remaining_time":3.920410033},
{"learn":[6.431317261],"iteration":48,"passed_time":0.1981910981,"remaining_time":3.846525189},
{"learn":[6.377586395],"iteration":49,"passed_time":0.1987414937,"remaining_time":3.77608838},
{"learn":[6.327558015],"iteration":50,"passed_time":0.1992630698,"remaining_time":3.707855945},
{"learn":[6.282040317],"iteration":51,"passed_time":0.1998110481,"remaining_time":3.642709107},
{"learn":[6.237655841],"iteration":52,"passed_time":0.2003732158,"remaining_time":3.580253497},
{"learn":[6.192792003],"iteration":53,"passed_time":0.2009002112,"remaining_time":3.519474071},
{"learn":[6.150579347],"iteration":54,"passed_time":0.2014491128,"remaining_time":3.461262029},
{"learn":[6.115693845],"iteration":55,"passed_time":0.2019542414,"remaining_time":3.404371498},
{"learn":[6.078780782],"iteration":56,"passed_time":0.2024823881,"remaining_time":3.34984021},
{"learn":[6.045146957],"iteration":57,"passed_time":0.2030111584,"remaining_time":3.297181229},
{"learn":[6.008080327],"iteration":58,"passed_time":0.2035760482,"remaining_time":3.246865447},
{"learn":[5.977575734],"iteration":59,"passed_time":0.2041197764,"remaining_time":3.197876497},
{"learn":[5.948036502],"iteration":60,"passed_time":0.2046669235,"remaining_time":3.150528543},
{"learn":[5.914888282],"iteration":61,"passed_time":0.2052145394,"remaining_time":3.104697386},
{"learn":[5.884957796],"iteration":62,"passed_time":0.2057528061,"remaining_time":3.060164751},
{"learn":[5.849539885],"iteration":63,"passed_time":0.2062614732,"remaining_time":3.016574046},
{"learn":[5.821387627],"iteration":64,"passed_time":0.2067875363,"remaining_time":2.974559176},
{"learn":[5.797012279],"iteration":65,"passed_time":0.2072911008,"remaining_time":2.933483154},
{"learn":[5.768685095],"iteration":66,"passed_time":0.207825453,"remaining_time":2.89404698},
{"learn":[5.755484587],"iteration":67,"passed_time":0.2081000868,"remaining_time":2.852195307},
{"learn":[5.731887055],"iteration":68,"passed_time":0.2086115272,"remaining_time":2.81474394},
{"learn":[5.707148487],"iteration":69,"passed_time":0.2091481907,"remaining_time":2.778683105},
{"learn":[5.685365039],"iteration":70,"passed_time":0.2096690599,"remaining_time":2.743416291},
{"learn":[5.663541834],"iteration":71,"passed_time":0.210216533,"remaining_time":2.709457537},
{"learn":[5.638108797],"iteration":72,"passed_time":0.2107119104,"remaining_time":2.675752616},
{"learn":[5.619204893],"iteration":73,"passed_time":0.2112153878,"remaining_time":2.643046609},
{"learn":[5.598472793],"iteration":74,"passed_time":0.2117497359,"remaining_time":2.611580076},
{"learn":[5.577007075],"iteration":75,"passed_time":0.2122370434,"remaining_time":2.580355633},
{"learn":[5.562637084],"iteration":76,"passed_time":0.2127243729,"remaining_time":2.549929821},
{"learn":[5.54729991],"iteration":77,"passed_time":0.2132070394,"remaining_time":2.520216543},
{"learn":[5.530737623],"iteration":78,"passed_time":0.213708289,"remaining_time":2.491459927},
{"learn":[5.513704873],"iteration":79,"passed_time":0.2142256001,"remaining_time":2.463594402},
{"learn":[5.501575529],"iteration":80,"passed_time":0.2147252881,"remaining_time":2.436204195},
{"learn":[5.484080734],"iteration":81,"passed_time":0.215266997,"remaining_time":2.409940283},
{"learn":[5.472178894],"iteration":82,"passed_time":0.2157919044,"remaining_time":2.384110558},
{"learn":[5.458923342],"iteration":83,"passed_time":0.2163174202,"remaining_time":2.358889963},
{"learn":[5.451382371],"iteration":84,"passed_time":0.2166850917,"remaining_time":2.332551281},
{"learn":[5.441410748],"iteration":85,"passed_time":0.2172726216,"remaining_time":2.309153211},
{"learn":[5.434047468],"iteration":86,"passed_time":0.2176088938,"remaining_time":2.28364276},
{"learn":[5.422107497],"iteration":87,"passed_time":0.2181546501,"remaining_time":2.260875464},
{"learn":[5.40731265],"iteration":88,"passed_time":0.2187008231,"remaining_time":2.238611796},
{"learn":[5.396360181],"iteration":89,"passed_time":0.2192423588,"remaining_time":2.21678385},
{"learn":[5.383793239],"iteration":90,"passed_time":0.2197682586,"remaining_time":2.19526755},
{"learn":[5.369605034],"iteration":91,"passed_time":0.2203019023,"remaining_time":2.174283993},
{"learn":[5.357467333],"iteration":92,"passed_time":0.2208208831,"remaining_time":2.153597215},
{"learn":[5.341109968],"iteration":93,"passed_time":0.221334216,"remaining_time":2.133285103},
{"learn":[5.330529276],"iteration":94,"passed_time":0.2218585734,"remaining_time":2.113494831},
{"learn":[5.319862075],"iteration":95,"passed_time":0.2223868689,"remaining_time":2.094143016},
{"learn":[5.313052243],"iteration":96,"passed_time":0.2229352601,"remaining_time":2.07536639},
{"learn":[5.299677207],"iteration":97,"passed_time":0.2235033064,"remaining_time":2.057142677},
{"learn":[5.287546698],"iteration":98,"passed_time":0.2240275233,"remaining_time":2.038876753},
{"learn":[5.279803754],"iteration":99,"passed_time":0.2245695758,"remaining_time":2.021126182},
{"learn":[5.272254612],"iteration":100,"passed_time":0.225189729,"remaining_time":2.004411548},
{"learn":[5.268813888],"iteration":101,"passed_time":0.2254568741,"remaining_time":1.984904637},
{"learn":[5.258113767],"iteration":102,"passed_time":0.2259859337,"remaining_time":1.968052257},
{"learn":[5.251018576],"iteration":103,"passed_time":0.2265347592,"remaining_time":1.951684079},
{"learn":[5.24171237],"iteration":104,"passed_time":0.2270746004,"remaining_time":1.935540641},
{"learn":[5.233984943],"iteration":105,"passed_time":0.2275959772,"remaining_time":1.919535884},
{"learn":[5.226240449],"iteration":106,"passed_time":0.2280982733,"remaining_time":1.903661291},
{"learn":[5.220541644],"iteration":107,"passed_time":0.2286085689,"remaining_time":1.88813744},
{"learn":[5.211712096],"iteration":108,"passed_time":0.2291783445,"remaining_time":1.873375275},
{"learn":[5.203388597],"iteration":109,"passed_time":0.2296922323,"remaining_time":1.85841897},
{"learn":[5.196026544],"iteration":110,"passed_time":0.2302722667,"remaining_time":1.844252658},
{"learn":[5.188716772],"iteration":111,"passed_time":0.2308861032,"remaining_time":1.830596961},
{"learn":[5.182163132],"iteration":112,"passed_time":0.2314508614,"remaining_time":1.81678685},
{"learn":[5.17764747],"iteration":113,"passed_time":0.2319735539,"remaining_time":1.802882182},
{"learn":[5.170548056],"iteration":114,"passed_time":0.2324893557,"remaining_time":1.789157216},
{"learn":[5.165901827],"iteration":115,"passed_time":0.2329103498,"remaining_time":1.774937493},
{"learn":[5.160333668],"iteration":116,"passed_time":0.2334826799,"remaining_time":1.762095781},
{"learn":[5.148953243],"iteration":117,"passed_time":0.2340425903,"remaining_time":1.749369192},
{"learn":[5.144729126],"iteration":118,"passed_time":0.2344604186,"remaining_time":1.7357952},
{"learn":[5.139939946],"iteration":119,"passed_time":0.2349983681,"remaining_time":1.723321366},
{"learn":[5.132898872],"iteration":120,"passed_time":0.2355537991,"remaining_time":1.711171813},
{"learn":[5.129073077],"iteration":121,"passed_time":0.2361036991,"remaining_time":1.699172523},
{"learn":[5.127123916],"iteration":122,"passed_time":0.2363739971,"remaining_time":1.685365817},
{"learn":[5.121282057],"iteration":123,"passed_time":0.2369107134,"remaining_time":1.673659556},
{"learn":[5.114489821],"iteration":124,"passed_time":0.237396148,"remaining_time":1.661773036},
{"learn":[5.107777291],"iteration":125,"passed_time":0.2379054855,"remaining_time":1.650233289},
{"learn":[5.103518754],"iteration":126,"passed_time":0.2383875316,"remaining_time":1.638679647},
{"learn":[5.101133351],"iteration":127,"passed_time":0.2387017134,"remaining_time":1.626155422},
{"learn":[5.096462705],"iteration":128,"passed_time":0.2392278484,"remaining_time":1.615251597},
{"learn":[5.08562082],"iteration":129,"passed_time":0.2397982348,"remaining_time":1.604803572},
{"learn":[5.080483682],"iteration":130,"passed_time":0.2403398949,"remaining_time":1.594315791},
{"learn":[5.07437499],"iteration":131,"passed_time":0.2408850939,"remaining_time":1.584001981},
{"learn":[5.070683732],"iteration":132,"passed_time":0.2413823978,"remaining_time":1.573522849},
{"learn":[5.06432037],"iteration":133,"passed_time":0.2418901389,"remaining_time":1.563260151},
{"learn":[5.057436484],"iteration":134,"passed_time":0.2424086864,"remaining_time":1.553211213},
{"learn":[5.053254656],"iteration":135,"passed_time":0.2429110037,"remaining_time":1.543199318},
{"learn":[5.04801663],"iteration":136,"passed_time":0.2434139006,"remaining_time":1.5333299},
{"learn":[5.045680836],"iteration":137,"passed_time":0.2438200085,"remaining_time":1.522991647},
{"learn":[5.041857933],"iteration":138,"passed_time":0.2443747723,"remaining_time":1.513717115},
{"learn":[5.035264888],"iteration":139,"passed_time":0.2450942958,"remaining_time":1.505579246},
{"learn":[5.028771948],"iteration":140,"passed_time":0.2456999633,"remaining_time":1.496852968},
{"learn":[5.024912247],"iteration":141,"passed_time":0.2462431298,"remaining_time":1.487863418},
{"learn":[5.02239068],"iteration":142,"passed_time":0.2467712445,"remaining_time":1.478901794},
{"learn":[5.017110572],"iteration":143,"passed_time":0.2472824882,"remaining_time":1.469957013},
{"learn":[5.010707886],"iteration":144,"passed_time":0.247848206,"remaining_time":1.461449766},
{"learn":[5.004389868],"iteration":145,"passed_time":0.2483537242,"remaining_time":1.452699181},
{"learn":[4.997628683],"iteration":146,"passed_time":0.2488700848,"remaining_time":1.44412369},
{"learn":[4.991497851],"iteration":147,"passed_time":0.2493905821,"remaining_time":1.435680918},
{"learn":[4.988345253],"iteration":148,"passed_time":0.2499630082,"remaining_time":1.427641073},
{"learn":[4.98460423],"iteration":149,"passed_time":0.2505148078,"remaining_time":1.419583911},
{"learn":[4.982441783],"iteration":150,"passed_time":0.2510660315,"remaining_time":1.411622919},
{"learn":[4.977461771],"iteration":151,"passed_time":0.2515966843,"remaining_time":1.40364466},
{"learn":[4.973601586],"iteration":152,"passed_time":0.252155349,"remaining_time":1.395918828},
{"learn":[4.968328804],"iteration":153,"passed_time":0.2526603872,"remaining_time":1.387991478},
{"learn":[4.9640736],"iteration":154,"passed_time":0.2531686464,"remaining_time":1.380177459},
{"learn":[4.960865882],"iteration":155,"passed_time":0.2536921117,"remaining_time":1.372539373},
{"learn":[4.957014156],"iteration":156,"passed_time":0.2542553994,"remaining_time":1.365205743},
{"learn":[4.952244852],"iteration":157,"passed_time":0.2547926649,"remaining_time":1.357819138},
{"learn":[4.949695675],"iteration":158,"passed_time":0.2553119009,"remaining_time":1.350423325},
{"learn":[4.946584698],"iteration":159,"passed_time":0.2558471875,"remaining_time":1.343197734},
{"learn":[4.940192834],"iteration":160,"passed_time":0.2563516612,"remaining_time":1.335894682},
{"learn":[4.936727994],"iteration":161,"passed_time":0.2569102296,"remaining_time":1.328955385},
{"learn":[4.932342063],"iteration":162,"passed_time":0.2574771427,"remaining_time":1.322137229},
{"learn":[4.925830838],"iteration":163,"passed_time":0.2579823657,"remaining_time":1.31508084},
{"learn":[4.922571773],"iteration":164,"passed_time":0.2585196376,"remaining_time":1.308266045},
{"learn":[4.918395814],"iteration":165,"passed_time":0.2592293439,"remaining_time":1.30239321},
{"learn":[4.911142452],"iteration":166,"passed_time":0.2599642305,"remaining_time":1.296707809},
{"learn":[4.908276131],"iteration":167,"passed_time":0.2607078703,"remaining_time":1.291124691},
{"learn":[4.904584645],"iteration":168,"passed_time":0.2615630989,"remaining_time":1.286147545},
{"learn":[4.89795517],"iteration":169,"passed_time":0.2621393851,"remaining_time":1.279856998},
{"learn":[4.895556491],"iteration":170,"passed_time":0.2627138057,"remaining_time":1.273624239},
{"learn":[4.890591233],"iteration":171,"passed_time":0.2632488199,"remaining_time":1.267267575},
{"learn":[4.884629277],"iteration":172,"passed_time":0.2637708584,"remaining_time":1.260916184},
{"learn":[4.880550786],"iteration":173,"passed_time":0.2642927348,"remaining_time":1.254631029},
{"learn":[4.876384842],"iteration":174,"passed_time":0.264847043,"remaining_time":1.248564631},
{"learn":[4.872638238],"iteration":175,"passed_time":0.2653722852,"remaining_time":1.24242479},
{"learn":[4.869137118],"iteration":176,"passed_time":0.2658645749,"remaining_time":1.23619517},
{"learn":[4.863587157],"iteration":177,"passed_time":0.2663730228,"remaining_time":1.230104633},
{"learn":[4.858028614],"iteration":178,"passed_time":0.2669452073,"remaining_time":1.2243688},
{"learn":[4.853838176],"iteration":179,"passed_time":0.2674699083,"remaining_time":1.218474027},
{"learn":[4.853462329],"iteration":180,"passed_time":0.267758697,"remaining_time":1.211571121},
{"learn":[4.851573196],"iteration":181,"passed_time":0.2682824272,"remaining_time":1.205796843},
{"learn":[4.848442087],"iteration":182,"passed_time":0.2688303431,"remaining_time":1.200187925},
{"learn":[4.845547104],"iteration":183,"passed_time":0.2694025336,"remaining_time":1.194741671},
{"learn":[4.839868817],"iteration":184,"passed_time":0.2699185038,"remaining_time":1.189100436},
{"learn":[4.836336958],"iteration":185,"passed_time":0.2704592214,"remaining_time":1.183622614},
{"learn":[4.831124789],"iteration":186,"passed_time":0.2709851765,"remaining_time":1.178133414},
{"learn":[4.827407333],"iteration":187,"passed_time":0.2715406143,"remaining_time":1.172824355},
{"learn":[4.824088918],"iteration":188,"passed_time":0.2721192922,"remaining_time":1.167665323},
{"learn":[4.820934539],"iteration":189,"passed_time":0.2726802087,"remaining_time":1.162478784},
{"learn":[4.816975227],"iteration":190,"passed_time":0.2733106675,"remaining_time":1.157635236},
{"learn":[4.812340486],"iteration":191,"passed_time":0.273908889,"remaining_time":1.152699908},
{"learn":[4.806402747],"iteration":192,"passed_time":0.2744264861,"remaining_time":1.147472406},
{"learn":[4.801521788],"iteration":193,"passed_time":0.2749860213,"remaining_time":1.142467697},
{"learn":[4.797601172],"iteration":194,"passed_time":0.2755002874,"remaining_time":1.137321699},
{"learn":[4.792694629],"iteration":195,"passed_time":0.2760422067,"remaining_time":1.132336399},
{"learn":[4.789794613],"iteration":196,"passed_time":0.2765976301,"remaining_time":1.127451254},
{"learn":[4.785367055],"iteration":197,"passed_time":0.2771197638,"remaining_time":1.122475003},
{"learn":[4.780376856],"iteration":198,"passed_time":0.2776567805,"remaining_time":1.117603423},
{"learn":[4.776691261],"iteration":199,"passed_time":0.2781472225,"remaining_time":1.11258889},
{"learn":[4.773470753],"iteration":200,"passed_time":0.2786753792,"remaining_time":1.107769294},
{"learn":[4.77207327],"iteration":201,"passed_time":0.279195752,"remaining_time":1.102961436},
{"learn":[4.767347177],"iteration":202,"passed_time":0.2797046232,"remaining_time":1.098150663},
{"learn":[4.763983068],"iteration":203,"passed_time":0.2802372905,"remaining_time":1.093474918},
{"learn":[4.761588849],"iteration":204,"passed_time":0.2807769909,"remaining_time":1.088866867},
{"learn":[4.758558086],"iteration":205,"passed_time":0.2813165184,"remaining_time":1.084297649},
{"learn":[4.753678804],"iteration":206,"passed_time":0.2818566692,"remaining_time":1.079769752},
{"learn":[4.746510889],"iteration":207,"passed_time":0.282379649,"remaining_time":1.075214817},
{"learn":[4.744840601],"iteration":208,"passed_time":0.2829427551,"remaining_time":1.070850331},
{"learn":[4.741702222],"iteration":209,"passed_time":0.2834853896,"remaining_time":1.066445037},
{"learn":[4.739352853],"iteration":210,"passed_time":0.2839499794,"remaining_time":1.06178452},
{"learn":[4.735539287],"iteration":211,"passed_time":0.2844760712,"remaining_time":1.057392189},
{"learn":[4.730726751],"iteration":212,"passed_time":0.2849740495,"remaining_time":1.052932286},
{"learn":[4.726416092],"iteration":213,"passed_time":0.2855037239,"remaining_time":1.048625827},
{"learn":[4.721293082],"iteration":214,"passed_time":0.2860164032,"remaining_time":1.044292449},
{"learn":[4.718443695],"iteration":215,"passed_time":0.2865982473,"remaining_time":1.04024549},
{"learn":[4.711627962],"iteration":216,"passed_time":0.2871295233,"remaining_time":1.036048004},
{"learn":[4.709790764],"iteration":217,"passed_time":0.2877689457,"remaining_time":1.03227209},
{"learn":[4.706913073],"iteration":218,"passed_time":0.2884061288,"remaining_time":1.028516834},
{"learn":[4.703846389],"iteration":219,"passed_time":0.2892068192,"remaining_time":1.025369632},
{"learn":[4.701001135],"iteration":220,"passed_time":0.2898213918,"remaining_time":1.021587621},
{"learn":[4.700380864],"iteration":221,"passed_time":0.2903258819,"remaining_time":1.017448361},
{"learn":[4.695837486],"iteration":222,"passed_time":0.2908561788,"remaining_time":1.013431618},
{"learn":[4.691242996],"iteration":223,"passed_time":0.2914097929,"remaining_time":1.009526783},
{"learn":[4.690284609],"iteration":224,"passed_time":0.2919353739,"remaining_time":1.005555177},
{"learn":[4.68827119],"iteration":225,"passed_time":0.2924512425,"remaining_time":1.001580804},
{"learn":[4.686922425],"iteration":226,"passed_time":0.2930126514,"remaining_time":0.9977919803},
{"learn":[4.686085874],"iteration":227,"passed_time":0.2935317686,"remaining_time":0.993888269},
{"learn":[4.683230741],"iteration":228,"passed_time":0.2940411917,"remaining_time":0.9899814796},
{"learn":[4.6773487],"iteration":229,"passed_time":0.2946136014,"remaining_time":0.9863151004},
{"learn":[4.671462906],"iteration":230,"passed_time":0.2951398489,"remaining_time":0.9825218346},
{"learn":[4.664799601],"iteration":231,"passed_time":0.295632463,"remaining_time":0.9786453947},
{"learn":[4.660979386],"iteration":232,"passed_time":0.2961828466,"remaining_time":0.9749881688},
{"learn":[4.656281279],"iteration":233,"passed_time":0.2966992068,"remaining_time":0.9712461215},
{"learn":[4.651997094],"iteration":234,"passed_time":0.2972211865,"remaining_time":0.9675498199},
{"learn":[4.650151977],"iteration":235,"passed_time":0.2977640082,"remaining_time":0.963947891},
{"learn":[4.648478046],"iteration":236,"passed_time":0.2982715465,"remaining_time":0.9602581856},
{"learn":[4.646364602],"iteration":237,"passed_time":0.2988137526,"remaining_time":0.9567062163},
{"learn":[4.642635873],"iteration":238,"passed_time":0.2993413217,"remaining_time":0.9531328277},
{"learn":[4.640860821],"iteration":239,"passed_time":0.299838962,"remaining_time":0.9494900463},
{"learn":[4.639446822],"iteration":240,"passed_time":0.3003637646,"remaining_time":0.94595891},
{"learn":[4.637120072],"iteration":241,"passed_time":0.3008823853,"remaining_time":0.9424332565},
{"learn":[4.633769267],"iteration":242,"passed_time":0.3014872419,"remaining_time":0.9392009964},
{"learn":[4.630491517],"iteration":243,"passed_time":0.302274509,"remaining_time":0.9365554459},
{"learn":[4.627813333],"iteration":244,"passed_time":0.3030579799,"remaining_time":0.9339133667},
{"learn":[4.622496304],"iteration":245,"passed_time":0.3036499756,"remaining_time":0.9306995187},
{"learn":[4.618979301],"iteration":246,"passed_time":0.30423044,"remaining_time":0.9274717463},
{"learn":[4.616563458],"iteration":247,"passed_time":0.3048474115,"remaining_time":0.924376022},
{"learn":[4.614759385],"iteration":248,"passed_time":0.3055988587,"remaining_time":0.9217057949},
{"learn":[4.61251363],"iteration":249,"passed_time":0.3062110792,"remaining_time":0.9186332377},
{"learn":[4.608796693],"iteration":250,"passed_time":0.3069250982,"remaining_time":0.9158840579},
{"learn":[4.60847774],"iteration":251,"passed_time":0.3075042481,"remaining_time":0.9127507048},
{"learn":[4.605195659],"iteration":252,"passed_time":0.3081729373,"remaining_time":0.9099019137},
{"learn":[4.60103766],"iteration":253,"passed_time":0.3089554982,"remaining_time":0.9074047309},
{"learn":[4.599325598],"iteration":254,"passed_time":0.3097412,"remaining_time":0.9049301726},
{"learn":[4.597012808],"iteration":255,"passed_time":0.3104418344,"remaining_time":0.9022215813},
{"learn":[4.594161533],"iteration":256,"passed_time":0.311286339,"remaining_time":0.8999445521},
{"learn":[4.592197259],"iteration":257,"passed_time":0.3120628033,"remaining_time":0.8974829458},
{"learn":[4.58952828],"iteration":258,"passed_time":0.3128604356,"remaining_time":0.8950949141},
{"learn":[4.585816572],"iteration":259,"passed_time":0.313636687,"remaining_time":0.892658263},
{"learn":[4.582934052],"iteration":260,"passed_time":0.3142791775,"remaining_time":0.8898556022},
{"learn":[4.582234842],"iteration":261,"passed_time":0.3149129788,"remaining_time":0.8870449557},
{"learn":[4.57571562],"iteration":262,"passed_time":0.3155912616,"remaining_time":0.8843755124},
{"learn":[4.571197349],"iteration":263,"passed_time":0.3163777038,"remaining_time":0.8820226894},
{"learn":[4.56723703],"iteration":264,"passed_time":0.317198669,"remaining_time":0.8797774406},
{"learn":[4.560335567],"iteration":265,"passed_time":0.3180238024,"remaining_time":0.8775544022},
{"learn":[4.554709345],"iteration":266,"passed_time":0.3188524148,"remaining_time":0.8753513859},
{"learn":[4.552806306],"iteration":267,"passed_time":0.3196161485,"remaining_time":0.8729814206},
{"learn":[4.550766241],"iteration":268,"passed_time":0.3203350909,"remaining_time":0.8705016782},
{"learn":[4.549216045],"iteration":269,"passed_time":0.3210701031,"remaining_time":0.8680784268},
{"learn":[4.547687452],"iteration":270,"passed_time":0.3218398811,"remaining_time":0.8657611561},
{"learn":[4.545642435],"iteration":271,"passed_time":0.3226064117,"remaining_time":0.8634465725},
{"learn":[4.543930359],"iteration":272,"passed_time":0.3233497294,"remaining_time":0.8610815139},
{"learn":[4.541029943],"iteration":273,"passed_time":0.3241154333,"remaining_time":0.8587876079},
{"learn":[4.537781449],"iteration":274,"passed_time":0.3248364537,"remaining_time":0.8563870143},
{"learn":[4.53066128],"iteration":275,"passed_time":0.325598603,"remaining_time":0.8541064803},
{"learn":[4.526763956],"iteration":276,"passed_time":0.326299359,"remaining_time":0.8516766663},
{"learn":[4.522036004],"iteration":277,"passed_time":0.3270241608,"remaining_time":0.8493217413},
{"learn":[4.515307629],"iteration":278,"passed_time":0.3276456224,"remaining_time":0.8467114473},
{"learn":[4.51109143],"iteration":279,"passed_time":0.3282179321,"remaining_time":0.8439889683},
{"learn":[4.508233494],"iteration":280,"passed_time":0.328883602,"remaining_time":0.8415206755},
{"learn":[4.502555629],"iteration":281,"passed_time":0.3296338228,"remaining_time":0.8392804423},
{"learn":[4.500081355],"iteration":282,"passed_time":0.3306274465,"remaining_time":0.8376674174},
{"learn":[4.495281743],"iteration":283,"passed_time":0.3313447852,"remaining_time":0.8353622049},
{"learn":[4.492138869],"iteration":284,"passed_time":0.3319818335,"remaining_time":0.832866705},
{"learn":[4.491708261],"iteration":285,"passed_time":0.3327440375,"remaining_time":0.8306966532},
{"learn":[4.489398865],"iteration":286,"passed_time":0.3334364788,"remaining_time":0.828363099},
{"learn":[4.485796373],"iteration":287,"passed_time":0.3341865124,"remaining_time":0.8261833224},
{"learn":[4.479542205],"iteration":288,"passed_time":0.3347982925,"remaining_time":0.8236733078},
{"learn":[4.475986993],"iteration":289,"passed_time":0.3355632019,"remaining_time":0.8215512874},
{"learn":[4.468661855],"iteration":290,"passed_time":0.3362268476,"remaining_time":0.8191918727},
{"learn":[4.463785664],"iteration":291,"passed_time":0.3369200561,"remaining_time":0.8169157526},
{"learn":[4.460445831],"iteration":292,"passed_time":0.3376459784,"remaining_time":0.8147293745},
{"learn":[4.45692492],"iteration":293,"passed_time":0.338337262,"remaining_time":0.8124697517},
{"learn":[4.454031688],"iteration":294,"passed_time":0.3391221394,"remaining_time":0.8104444349},
{"learn":[4.451672391],"iteration":295,"passed_time":0.3399336327,"remaining_time":0.808490802},
{"learn":[4.45031553],"iteration":296,"passed_time":0.3406445831,"remaining_time":0.8063068752},
{"learn":[4.446782666],"iteration":297,"passed_time":0.3414247291,"remaining_time":0.8042958384},
{"learn":[4.444369689],"iteration":298,"passed_time":0.3420951951,"remaining_time":0.8020358922},
{"learn":[4.44411683],"iteration":299,"passed_time":0.3429002457,"remaining_time":0.8001005733},
{"learn":[4.440876943],"iteration":300,"passed_time":0.3434981656,"remaining_time":0.7976917534},
{"learn":[4.439336453],"iteration":301,"passed_time":0.344227316,"remaining_time":0.7955982336},
{"learn":[4.436666901],"iteration":302,"passed_time":0.345061803,"remaining_time":0.7937560286},
{"learn":[4.433043336],"iteration":303,"passed_time":0.3459868908,"remaining_time":0.7921278815},
{"learn":[4.431419305],"iteration":304,"passed_time":0.3467504553,"remaining_time":0.7901362834},
{"learn":[4.428859646],"iteration":305,"passed_time":0.3475250759,"remaining_time":0.7881777864},
{"learn":[4.424552441],"iteration":306,"passed_time":0.3483642974,"remaining_time":0.7863728277},
{"learn":[4.422706391],"iteration":307,"passed_time":0.3490781432,"remaining_time":0.7842924516},
{"learn":[4.421427994],"iteration":308,"passed_time":0.3498976464,"remaining_time":0.7824571962},
{"learn":[4.418733158],"iteration":309,"passed_time":0.3508238474,"remaining_time":0.7808659829},
{"learn":[4.415656941],"iteration":310,"passed_time":0.3514774007,"remaining_time":0.7786750132},
{"learn":[4.410747417],"iteration":311,"passed_time":0.3521439526,"remaining_time":0.7765225621},
{"learn":[4.408126521],"iteration":312,"passed_time":0.3529030913,"remaining_time":0.7745828235},
{"learn":[4.407843853],"iteration":313,"passed_time":0.3535672251,"remaining_time":0.7724430459},
{"learn":[4.405219398],"iteration":314,"passed_time":0.3542679103,"remaining_time":0.7703921225},
{"learn":[4.402708465],"iteration":315,"passed_time":0.354980556,"remaining_time":0.7683756339},
{"learn":[4.40104971],"iteration":316,"passed_time":0.3556686051,"remaining_time":0.7663143764},
{"learn":[4.400830038],"iteration":317,"passed_time":0.356420376,"remaining_time":0.7643984165},
{"learn":[4.39784288],"iteration":318,"passed_time":0.3572682411,"remaining_time":0.7626948972},
{"learn":[4.393741845],"iteration":319,"passed_time":0.3581091207,"remaining_time":0.7609818816},
{"learn":[4.393425936],"iteration":320,"passed_time":0.3591494608,"remaining_time":0.7596962114},
{"learn":[4.390505974],"iteration":321,"passed_time":0.3599381767,"remaining_time":0.7578822478},
{"learn":[4.390305136],"iteration":322,"passed_time":0.3608736305,"remaining_time":0.7563821915},
{"learn":[4.38568203],"iteration":323,"passed_time":0.3616510012,"remaining_time":0.7545557926},
{"learn":[4.383057135],"iteration":324,"passed_time":0.3624379655,"remaining_time":0.7527557744},
{"learn":[4.380662684],"iteration":325,"passed_time":0.363190278,"remaining_time":0.7508903293},
{"learn":[4.37805727],"iteration":326,"passed_time":0.3638891503,"remaining_time":0.7489217069},
{"learn":[4.373708319],"iteration":327,"passed_time":0.3647398943,"remaining_time":0.7472719786},
{"learn":[4.36887921],"iteration":328,"passed_time":0.3654993291,"remaining_time":0.7454408809},
{"learn":[4.367895929],"iteration":329,"passed_time":0.3661942069,"remaining_time":0.7434852079},
{"learn":[4.362140573],"iteration":330,"passed_time":0.366926755,"remaining_time":0.7416132903},
{"learn":[4.361931924],"iteration":331,"passed_time":0.3676584402,"remaining_time":0.7397465002},
{"learn":[4.359656377],"iteration":332,"passed_time":0.3683653461,"remaining_time":0.7378368945},
{"learn":[4.354281355],"iteration":333,"passed_time":0.369203864,"remaining_time":0.7361969265},
{"learn":[4.348589447],"iteration":334,"passed_time":0.3699397219,"remaining_time":0.7343579554},
{"learn":[4.346355698],"iteration":335,"passed_time":0.3707416255,"remaining_time":0.7326560695},
{"learn":[4.343894047],"iteration":336,"passed_time":0.3715284618,"remaining_time":0.7309298818},
{"learn":[4.341561356],"iteration":337,"passed_time":0.3722890434,"remaining_time":0.7291578306},
{"learn":[4.338869061],"iteration":338,"passed_time":0.3732813051,"remaining_time":0.7278434887},
{"learn":[4.333720063],"iteration":339,"passed_time":0.3742646228,"remaining_time":0.7265136796},
{"learn":[4.330892223],"iteration":340,"passed_time":0.3752352945,"remaining_time":0.7251614635},
{"learn":[4.328311474],"iteration":341,"passed_time":0.3761657841,"remaining_time":0.7237341694},
{"learn":[4.324580133],"iteration":342,"passed_time":0.3769878717,"remaining_time":0.7221021333},
{"learn":[4.323354432],"iteration":343,"passed_time":0.3778673213,"remaining_time":0.7205841941},
{"learn":[4.323159553],"iteration":344,"passed_time":0.3785737244,"remaining_time":0.7187414187},
{"learn":[4.318639682],"iteration":345,"passed_time":0.3791969333,"remaining_time":0.7167479606},
{"learn":[4.312712208],"iteration":346,"passed_time":0.3798536752,"remaining_time":0.714825504},
{"learn":[4.311461062],"iteration":347,"passed_time":0.3805215419,"remaining_time":0.7129311646},
{"learn":[4.311178356],"iteration":348,"passed_time":0.3811287978,"remaining_time":0.7109307947},
{"learn":[4.311102505],"iteration":349,"passed_time":0.3816958144,"remaining_time":0.7088636554},
{"learn":[4.310232308],"iteration":350,"passed_time":0.3823278801,"remaining_time":0.7069253396},
{"learn":[4.305128197],"iteration":351,"passed_time":0.3831474869,"remaining_time":0.7053396918},
{"learn":[4.304595496],"iteration":352,"passed_time":0.3838545012,"remaining_time":0.7035520177},
{"learn":[4.3004992],"iteration":353,"passed_time":0.3846334871,"remaining_time":0.7019017872},
{"learn":[4.297581524],"iteration":354,"passed_time":0.3854439075,"remaining_time":0.7003135785},
{"learn":[4.297355825],"iteration":355,"passed_time":0.3862876089,"remaining_time":0.6987899441},
{"learn":[4.295758715],"iteration":356,"passed_time":0.3873319574,"remaining_time":0.6976315088},
{"learn":[4.292500657],"iteration":357,"passed_time":0.3881573412,"remaining_time":0.6960810421},
{"learn":[4.290797586],"iteration":358,"passed_time":0.3889543335,"remaining_time":0.6944839214},
{"learn":[4.286410608],"iteration":359,"passed_time":0.3897549291,"remaining_time":0.6928976518},
{"learn":[4.280278245],"iteration":360,"passed_time":0.3906149855,"remaining_time":0.6914209855},
{"learn":[4.279941283],"iteration":361,"passed_time":0.3912390241,"remaining_time":0.6895317607},
{"learn":[4.274426275],"iteration":362,"passed_time":0.3919017794,"remaining_time":0.6877174476},
{"learn":[4.273567658],"iteration":363,"passed_time":0.3927399629,"remaining_time":0.6862159791},
{"learn":[4.269488271],"iteration":364,"passed_time":0.3936313294,"remaining_time":0.6848106689},
{"learn":[4.266838205],"iteration":365,"passed_time":0.3945682424,"remaining_time":0.6834870647},
{"learn":[4.263456509],"iteration":366,"passed_time":0.3953961843,"remaining_time":0.6819776149},
{"learn":[4.260360204],"iteration":367,"passed_time":0.3962341058,"remaining_time":0.6804890079},
{"learn":[4.255120549],"iteration":368,"passed_time":0.3970007741,"remaining_time":0.6788820825},
{"learn":[4.252582211],"iteration":369,"passed_time":0.3978366091,"remaining_time":0.6773974696},
{"learn":[4.247857931],"iteration":370,"passed_time":0.398523351,"remaining_time":0.6756635789},
{"learn":[4.245288911],"iteration":371,"passed_time":0.399328458,"remaining_time":0.6741351388},
{"learn":[4.24048515],"iteration":372,"passed_time":0.4001624125,"remaining_time":0.6726590688},
{"learn":[4.2378365],"iteration":373,"passed_time":0.4010028742,"remaining_time":0.6711973241},
{"learn":[4.236751063],"iteration":374,"passed_time":0.4017112389,"remaining_time":0.6695187315},
{"learn":[4.233240093],"iteration":375,"passed_time":0.4023787296,"remaining_time":0.6677774661},
{"learn":[4.230358421],"iteration":376,"passed_time":0.4030140862,"remaining_time":0.665988795},
{"learn":[4.225853583],"iteration":377,"passed_time":0.4037094028,"remaining_time":0.6643048903},
{"learn":[4.224702126],"iteration":378,"passed_time":0.4044377931,"remaining_time":0.6626803945},
{"learn":[4.224361982],"iteration":379,"passed_time":0.405215591,"remaining_time":0.6611412275},
{"learn":[4.223787954],"iteration":380,"passed_time":0.4061409724,"remaining_time":0.6598458319},
{"learn":[4.22144054],"iteration":381,"passed_time":0.4070345034,"remaining_time":0.6585008458},
{"learn":[4.217739335],"iteration":382,"passed_time":0.4079098192,"remaining_time":0.6571288732},
{"learn":[4.215611665],"iteration":383,"passed_time":0.4086224181,"remaining_time":0.6554984623},
{"learn":[4.210236863],"iteration":384,"passed_time":0.4093182975,"remaining_time":0.6538461116},
{"learn":[4.208454294],"iteration":385,"passed_time":0.410196495,"remaining_time":0.6524887253},
{"learn":[4.207446501],"iteration":386,"passed_time":0.41086996,"remaining_time":0.6508095231},
{"learn":[4.204985442],"iteration":387,"passed_time":0.4115430621,"remaining_time":0.649134933},
{"learn":[4.202796622],"iteration":388,"passed_time":0.4122660434,"remaining_time":0.6475438368},
{"learn":[4.199774004],"iteration":389,"passed_time":0.4131168526,"remaining_time":0.6461571285},
{"learn":[4.199458358],"iteration":390,"passed_time":0.4139417172,"remaining_time":0.6447327514},
{"learn":[4.19751254],"iteration":391,"passed_time":0.4147391187,"remaining_time":0.6432688372},
{"learn":[4.195201346],"iteration":392,"passed_time":0.4155746277,"remaining_time":0.6418671731},
{"learn":[4.190593508],"iteration":393,"passed_time":0.4163820348,"remaining_time":0.6404251601},
{"learn":[4.187212054],"iteration":394,"passed_time":0.4171924952,"remaining_time":0.638991037},
{"learn":[4.184984466],"iteration":395,"passed_time":0.4179600459,"remaining_time":0.6374946155},
{"learn":[4.182832144],"iteration":396,"passed_time":0.4186852261,"remaining_time":0.6359375097},
{"learn":[4.179752812],"iteration":397,"passed_time":0.4364239239,"remaining_time":0.6601185985},
{"learn":[4.17878934],"iteration":398,"passed_time":0.44230686,"remaining_time":0.6662316362},
{"learn":[4.174548229],"iteration":399,"passed_time":0.4446803797,"remaining_time":0.6670205696},
{"learn":[4.168872556],"iteration":400,"passed_time":0.4456221862,"remaining_time":0.6656550861},
{"learn":[4.163926494],"iteration":401,"passed_time":0.4465092849,"remaining_time":0.6642103292},
{"learn":[4.159485076],"iteration":402,"passed_time":0.447412661,"remaining_time":0.6627924531},
{"learn":[4.155926102],"iteration":403,"passed_time":0.4482333454,"remaining_time":0.6612551333},
{"learn":[4.153540115],"iteration":404,"passed_time":0.4492222998,"remaining_time":0.6599685638},
{"learn":[4.150983044],"iteration":405,"passed_time":0.4505117325,"remaining_time":0.6591230766},
{"learn":[4.146539132],"iteration":406,"passed_time":0.4517258487,"remaining_time":0.6581656714},
{"learn":[4.144869174],"iteration":407,"passed_time":0.453100086,"remaining_time":0.6574393405},
{"learn":[4.142825962],"iteration":408,"passed_time":0.4543594904,"remaining_time":0.6565439091},
{"learn":[4.142467378],"iteration":409,"passed_time":0.4554728061,"remaining_time":0.6554364771},
{"learn":[4.141800768],"iteration":410,"passed_time":0.4564092348,"remaining_time":0.6540755214},
{"learn":[4.140107084],"iteration":411,"passed_time":0.4572478911,"remaining_time":0.6525770873},
{"learn":[4.136243196],"iteration":412,"passed_time":0.458105337,"remaining_time":0.6511085541},
{"learn":[4.133618439],"iteration":413,"passed_time":0.4589847466,"remaining_time":0.6496740616},
{"learn":[4.131053025],"iteration":414,"passed_time":0.4598300396,"remaining_time":0.6481941522},
{"learn":[4.128379975],"iteration":415,"passed_time":0.4606437565,"remaining_time":0.6466729659},
{"learn":[4.127068571],"iteration":416,"passed_time":0.461401716,"remaining_time":0.6450772193},
{"learn":[4.125969877],"iteration":417,"passed_time":0.462205397,"remaining_time":0.6435491412},
{"learn":[4.123893633],"iteration":418,"passed_time":0.4630053454,"remaining_time":0.6420193452},
{"learn":[4.119643722],"iteration":419,"passed_time":0.4638356606,"remaining_time":0.6405349598},
{"learn":[4.11465686],"iteration":420,"passed_time":0.4646144513,"remaining_time":0.6389828202},
{"learn":[4.111565986],"iteration":421,"passed_time":0.4653642321,"remaining_time":0.6373946117},
{"learn":[4.106322452],"iteration":422,"passed_time":0.4661601591,"remaining_time":0.635873314},
{"learn":[4.104222175],"iteration":423,"passed_time":0.4669490247,"remaining_time":0.6343458449},
{"learn":[4.103008002],"iteration":424,"passed_time":0.4677208208,"remaining_time":0.6327987575},
{"learn":[4.099176337],"iteration":425,"passed_time":0.4685106879,"remaining_time":0.6312796593},
{"learn":[4.096525716],"iteration":426,"passed_time":0.4692584302,"remaining_time":0.6297074485},
{"learn":[4.094967724],"iteration":427,"passed_time":0.4700778682,"remaining_time":0.628234908},
{"learn":[4.094683584],"iteration":428,"passed_time":0.4708408099,"remaining_time":0.6266902155},
{"learn":[4.091096563],"iteration":429,"passed_time":0.4716131248,"remaining_time":0.6251615841},
{"learn":[4.089178677],"iteration":430,"passed_time":0.4724074002,"remaining_time":0.6236654541},
{"learn":[4.085335077],"iteration":431,"passed_time":0.4732148601,"remaining_time":0.6221899086},
{"learn":[4.084852122],"iteration":432,"passed_time":0.4739610743,"remaining_time":0.6206372497},
{"learn":[4.080322952],"iteration":433,"passed_time":0.4748072702,"remaining_time":0.6192186979},
{"learn":[4.077449519],"iteration":434,"passed_time":0.4755846744,"remaining_time":0.6177134277},
{"learn":[4.076568374],"iteration":435,"passed_time":0.4763404815,"remaining_time":0.6161835586},
{"learn":[4.076071793],"iteration":436,"passed_time":0.477044194,"remaining_time":0.6145901172},
{"learn":[4.075027644],"iteration":437,"passed_time":0.4780010463,"remaining_time":0.6133255434},
{"learn":[4.07020837],"iteration":438,"passed_time":0.4787957549,"remaining_time":0.6118551674},
{"learn":[4.06833694],"iteration":439,"passed_time":0.4795579361,"remaining_time":0.6103464642},
{"learn":[4.063936568],"iteration":440,"passed_time":0.4803225895,"remaining_time":0.6088442801},
{"learn":[4.061734926],"iteration":441,"passed_time":0.4810261589,"remaining_time":0.6072683182},
{"learn":[4.060815619],"iteration":442,"passed_time":0.4817797126,"remaining_time":0.605759142},
{"learn":[4.056407489],"iteration":443,"passed_time":0.4824457192,"remaining_time":0.6041437385},
{"learn":[4.05238936],"iteration":444,"passed_time":0.4831988093,"remaining_time":0.6026412117},
{"learn":[4.049685254],"iteration":445,"passed_time":0.483820433,"remaining_time":0.6009787441},
{"learn":[4.045162016],"iteration":446,"passed_time":0.4844979025,"remaining_time":0.5993900226},
{"learn":[4.042955482],"iteration":447,"passed_time":0.4852215338,"remaining_time":0.5978622471},
{"learn":[4.041467663],"iteration":448,"passed_time":0.4859281925,"remaining_time":0.5963172251},
{"learn":[4.038920476],"iteration":449,"passed_time":0.4867183201,"remaining_time":0.5948779468},
{"learn":[4.036694383],"iteration":450,"passed_time":0.4874398214,"remaining_time":0.5933580087},
{"learn":[4.034999007],"iteration":451,"passed_time":0.4882172116,"remaining_time":0.5919093628},
{"learn":[4.031928018],"iteration":452,"passed_time":0.4889597745,"remaining_time":0.5904216262},
{"learn":[4.028718143],"iteration":453,"passed_time":0.4897201466,"remaining_time":0.5889585903},
{"learn":[4.027401978],"iteration":454,"passed_time":0.490346232,"remaining_time":0.5873377944},
{"learn":[4.025930598],"iteration":455,"passed_time":0.4910301869,"remaining_time":0.5857903985},
{"learn":[4.021074523],"iteration":456,"passed_time":0.4916478964,"remaining_time":0.5841680695},
{"learn":[4.020268486],"iteration":457,"passed_time":0.4923721538,"remaining_time":0.582676217},
{"learn":[4.017986361],"iteration":458,"passed_time":0.4931093325,"remaining_time":0.5812029387},
{"learn":[4.014814804],"iteration":459,"passed_time":0.4939154067,"remaining_time":0.5798137383},
{"learn":[4.009704796],"iteration":460,"passed_time":0.4947187669,"remaining_time":0.5784238944},
{"learn":[4.008440457],"iteration":461,"passed_time":0.4954150031,"remaining_time":0.5769118434},
{"learn":[4.004854849],"iteration":462,"passed_time":0.4963039959,"remaining_time":0.5756268807},
{"learn":[4.000898028],"iteration":463,"passed_time":0.4970945215,"remaining_time":0.5742298782},
{"learn":[3.996617985],"iteration":464,"passed_time":0.4978923766,"remaining_time":0.5728439171},
{"learn":[3.995443319],"iteration":465,"passed_time":0.4986929122,"remaining_time":0.5714635517},
{"learn":[3.990771995],"iteration":466,"passed_time":0.4995417109,"remaining_time":0.5701407536},
{"learn":[3.989249359],"iteration":467,"passed_time":0.5003239078,"remaining_time":0.5687442713},
{"learn":[3.986599538],"iteration":468,"passed_time":0.501067486,"remaining_time":0.5673066845},
{"learn":[3.985628919],"iteration":469,"passed_time":0.5018021493,"remaining_time":0.5658619982},
{"learn":[3.985086112],"iteration":470,"passed_time":0.5025725201,"remaining_time":0.5644604313},
{"learn":[3.98466839],"iteration":471,"passed_time":0.5033605869,"remaining_time":0.5630813345},
{"learn":[3.984233894],"iteration":472,"passed_time":0.5039804208,"remaining_time":0.5615172976},
{"learn":[3.981855845],"iteration":473,"passed_time":0.5046272043,"remaining_time":0.5599871508},
{"learn":[3.978684264],"iteration":474,"passed_time":0.5054175507,"remaining_time":0.5586193982},
{"learn":[3.974361269],"iteration":475,"passed_time":0.5062787168,"remaining_time":0.5573320327},
{"learn":[3.972074049],"iteration":476,"passed_time":0.5071516129,"remaining_time":0.5560593156},
{"learn":[3.97191982],"iteration":477,"passed_time":0.5079306896,"remaining_time":0.5546858159},
{"learn":[3.969616848],"iteration":478,"passed_time":0.508729318,"remaining_time":0.553336064},
{"learn":[3.968533527],"iteration":479,"passed_time":0.5095285319,"remaining_time":0.5519892429},
{"learn":[3.967568753],"iteration":480,"passed_time":0.5102825533,"remaining_time":0.5505959359},
{"learn":[3.966232553],"iteration":481,"passed_time":0.5111097928,"remaining_time":0.5492839682},
{"learn":[3.961522393],"iteration":482,"passed_time":0.5118738577,"remaining_time":0.547906386},
{"learn":[3.955829553],"iteration":483,"passed_time":0.5127069114,"remaining_time":0.5466048891},
{"learn":[3.954248095],"iteration":484,"passed_time":0.5134584439,"remaining_time":0.54521876},
{"learn":[3.951922606],"iteration":485,"passed_time":0.5141740493,"remaining_time":0.5437972456},
{"learn":[3.94978202],"iteration":486,"passed_time":0.5149844289,"remaining_time":0.5424784641},
{"learn":[3.949518999],"iteration":487,"passed_time":0.5159081471,"remaining_time":0.5412806789},
{"learn":[3.945431216],"iteration":488,"passed_time":0.51668274,"remaining_time":0.5399281803},
{"learn":[3.943249086],"iteration":489,"passed_time":0.5173730148,"remaining_time":0.5384902808},
{"learn":[3.941981548],"iteration":490,"passed_time":0.5181283175,"remaining_time":0.5371228383},
{"learn":[3.936600517],"iteration":491,"passed_time":0.5189760702,"remaining_time":0.5358533407},
{"learn":[3.934476885],"iteration":492,"passed_time":0.5197688711,"remaining_time":0.5345290418},
{"learn":[3.93045798],"iteration":493,"passed_time":0.520637709,"remaining_time":0.5332847789},
{"learn":[3.925977375],"iteration":494,"passed_time":0.5215844993,"remaining_time":0.5321215599},
{"learn":[3.92457993],"iteration":495,"passed_time":0.5225046465,"remaining_time":0.5309321408},
{"learn":[3.919849146],"iteration":496,"passed_time":0.5233292899,"remaining_time":0.5296471485},
{"learn":[3.919681964],"iteration":497,"passed_time":0.5241175182,"remaining_time":0.5283272974},
{"learn":[3.917633027],"iteration":498,"passed_time":0.5249057233,"remaining_time":0.5270095539},
{"learn":[3.916616419],"iteration":499,"passed_time":0.5257177602,"remaining_time":0.5257177602},
{"learn":[3.912896166],"iteration":500,"passed_time":0.5265167949,"remaining_time":0.5244149315},
{"learn":[3.912769674],"iteration":501,"passed_time":0.5272009251,"remaining_time":0.5230001209},
{"learn":[3.909373788],"iteration":502,"passed_time":0.5280619151,"remaining_time":0.5217629658},
{"learn":[3.906706036],"iteration":503,"passed_time":0.52894367,"remaining_time":0.5205477387},
{"learn":[3.903895664],"iteration":504,"passed_time":0.5297496426,"remaining_time":0.5192595507},
{"learn":[3.902982967],"iteration":505,"passed_time":0.5305395442,"remaining_time":0.5179575787},
{"learn":[3.900905528],"iteration":506,"passed_time":0.5312865421,"remaining_time":0.5166159078},
{"learn":[3.897463465],"iteration":507,"passed_time":0.5320061297,"remaining_time":0.5152500311},
{"learn":[3.895918033],"iteration":508,"passed_time":0.5327918435,"remaining_time":0.5139504816},
{"learn":[3.893921936],"iteration":509,"passed_time":0.5335748028,"remaining_time":0.5126503007},
{"learn":[3.890237934],"iteration":510,"passed_time":0.5343066113,"remaining_time":0.5113031955},
{"learn":[3.887311613],"iteration":511,"passed_time":0.5350335543,"remaining_time":0.5099538565},
{"learn":[3.884869735],"iteration":512,"passed_time":0.5359193294,"remaining_time":0.5087577259},
{"learn":[3.882101231],"iteration":513,"passed_time":0.5367092805,"remaining_time":0.5074721991},
{"learn":[3.88060368],"iteration":514,"passed_time":0.5375304846,"remaining_time":0.5062180292},
{"learn":[3.877726076],"iteration":515,"passed_time":0.5382601762,"remaining_time":0.5048797001},
{"learn":[3.874938145],"iteration":516,"passed_time":0.5390114754,"remaining_time":0.5035639122},
{"learn":[3.874340833],"iteration":517,"passed_time":0.5397674853,"remaining_time":0.502254687},
{"learn":[3.873105224],"iteration":518,"passed_time":0.5405118358,"remaining_time":0.5009367881},
{"learn":[3.869800236],"iteration":519,"passed_time":0.5412919594,"remaining_time":0.4996541164},
{"learn":[3.867932518],"iteration":520,"passed_time":0.5420945399,"remaining_time":0.4983940204},
{"learn":[3.866666962],"iteration":521,"passed_time":0.5428493685,"remaining_time":0.4970919505},
{"learn":[3.865527652],"iteration":522,"passed_time":0.543621073,"remaining_time":0.4958073648},
{"learn":[3.861900081],"iteration":523,"passed_time":0.5444024526,"remaining_time":0.4945335257},
{"learn":[3.858502887],"iteration":524,"passed_time":0.5451957807,"remaining_time":0.493272373},
{"learn":[3.858335097],"iteration":525,"passed_time":0.5459913702,"remaining_time":0.492015037},
{"learn":[3.855719306],"iteration":526,"passed_time":0.5468100509,"remaining_time":0.4907801785},
{"learn":[3.855137428],"iteration":527,"passed_time":0.547528006,"remaining_time":0.4894568539},
{"learn":[3.851985706],"iteration":528,"passed_time":0.5482919634,"remaining_time":0.4881767765},
{"learn":[3.851051809],"iteration":529,"passed_time":0.5490709097,"remaining_time":0.4869119388},
{"learn":[3.850679146],"iteration":530,"passed_time":0.5499099289,"remaining_time":0.4857019899},
{"learn":[3.848179484],"iteration":531,"passed_time":0.550738962,"remaining_time":0.4844846508},
{"learn":[3.844551071],"iteration":532,"passed_time":0.5515503041,"remaining_time":0.4832532683},
{"learn":[3.841604794],"iteration":533,"passed_time":0.55230758,"remaining_time":0.4819762776},
{"learn":[3.83969656],"iteration":534,"passed_time":0.5531659435,"remaining_time":0.4807890911},
{"learn":[3.836811463],"iteration":535,"passed_time":0.5539871799,"remaining_time":0.4795709916},
{"learn":[3.834182551],"iteration":536,"passed_time":0.554733903,"remaining_time":0.4782901249},
{"learn":[3.828012842],"iteration":537,"passed_time":0.5555122685,"remaining_time":0.4770384165},
{"learn":[3.826636176],"iteration":538,"passed_time":0.556204127,"remaining_time":0.475714476},
{"learn":[3.826189798],"iteration":539,"passed_time":0.5568861875,"remaining_time":0.4743845301},
{"learn":[3.824104738],"iteration":540,"passed_time":0.5577206464,"remaining_time":0.4731862786},
{"learn":[3.82300218],"iteration":541,"passed_time":0.5584503544,"remaining_time":0.471900853},
{"learn":[3.817146402],"iteration":542,"passed_time":0.5592401912,"remaining_time":0.4706680799},
{"learn":[3.814638044],"iteration":543,"passed_time":0.5601304768,"remaining_time":0.469521135},
{"learn":[3.812979573],"iteration":544,"passed_time":0.560859256,"remaining_time":0.4682402963},
{"learn":[3.811938825],"iteration":545,"passed_time":0.5615580911,"remaining_time":0.4669365812},
{"learn":[3.811479418],"iteration":546,"passed_time":0.5622409336,"remaining_time":0.4656218335},
{"learn":[3.80742981],"iteration":547,"passed_time":0.5630849374,"remaining_time":0.4644423206},
{"learn":[3.805097043],"iteration":548,"passed_time":0.5638940637,"remaining_time":0.4632353784},
{"learn":[3.801577232],"iteration":549,"passed_time":0.5646238541,"remaining_time":0.4619649715},
{"learn":[3.799762083],"iteration":550,"passed_time":0.5654375987,"remaining_time":0.4607649397},
{"learn":[3.796393455],"iteration":551,"passed_time":0.5661688795,"remaining_time":0.4594993805},
{"learn":[3.793486459],"iteration":552,"passed_time":0.5669845201,"remaining_time":0.458303943},
{"learn":[3.792006091],"iteration":553,"passed_time":0.5676851329,"remaining_time":0.4570172731},
{"learn":[3.78932128],"iteration":554,"passed_time":0.5684022072,"remaining_time":0.4557459139},
{"learn":[3.787581812],"iteration":555,"passed_time":0.569162616,"remaining_time":0.4545111538},
{"learn":[3.785308865],"iteration":556,"passed_time":0.5697699167,"remaining_time":0.4531563251},
{"learn":[3.78465475],"iteration":557,"passed_time":0.5704842305,"remaining_time":0.4518889424},
{"learn":[3.780498869],"iteration":558,"passed_time":0.5711964138,"remaining_time":0.4506218577},
{"learn":[3.778734909],"iteration":559,"passed_time":0.5719241353,"remaining_time":0.4493689634},
{"learn":[3.778652349],"iteration":560,"passed_time":0.5726738468,"remaining_time":0.4481351493},
{"learn":[3.777928006],"iteration":561,"passed_time":0.5733996771,"remaining_time":0.4468844458},
{"learn":[3.776131406],"iteration":562,"passed_time":0.574348139,"remaining_time":0.4458084134},
{"learn":[3.772925617],"iteration":563,"passed_time":0.5752291986,"remaining_time":0.444680728},
{"learn":[3.7727745],"iteration":564,"passed_time":0.5759701939,"remaining_time":0.4434460785},
{"learn":[3.771763073],"iteration":565,"passed_time":0.5767968493,"remaining_time":0.4422788562},
{"learn":[3.768738162],"iteration":566,"passed_time":0.5778004171,"remaining_time":0.4412479375},
{"learn":[3.767220794],"iteration":567,"passed_time":0.5786391878,"remaining_time":0.4400917766},
{"learn":[3.766691102],"iteration":568,"passed_time":0.5794399794,"remaining_time":0.4389079633},
{"learn":[3.766259335],"iteration":569,"passed_time":0.5802426799,"remaining_time":0.437726934},
{"learn":[3.76116362],"iteration":570,"passed_time":0.5810462793,"remaining_time":0.4365479051},
{"learn":[3.758633056],"iteration":571,"passed_time":0.5818830911,"remaining_time":0.4353950402},
{"learn":[3.754603809],"iteration":572,"passed_time":0.5826931703,"remaining_time":0.4342233573},
{"learn":[3.754070549],"iteration":573,"passed_time":0.5834841056,"remaining_time":0.4330387264},
{"learn":[3.750534319],"iteration":574,"passed_time":0.5842609862,"remaining_time":0.4318450768},
{"learn":[3.746491516],"iteration":575,"passed_time":0.5850697842,"remaining_time":0.4306763689},
{"learn":[3.744210544],"iteration":576,"passed_time":0.5858721051,"remaining_time":0.4295041602},
{"learn":[3.742929991],"iteration":577,"passed_time":0.586609495,"remaining_time":0.428285825},
{"learn":[3.740402992],"iteration":578,"passed_time":0.5873774649,"remaining_time":0.4270913864},
{"learn":[3.739644243],"iteration":579,"passed_time":0.5880785997,"remaining_time":0.4258500205},
{"learn":[3.737529404],"iteration":580,"passed_time":0.5887812582,"remaining_time":0.4246116131},
{"learn":[3.737196923],"iteration":581,"passed_time":0.5895037603,"remaining_time":0.4233892986},
{"learn":[3.733954464],"iteration":582,"passed_time":0.5902155496,"remaining_time":0.4221610363},
{"learn":[3.731608623],"iteration":583,"passed_time":0.5909943275,"remaining_time":0.4209822607},
{"learn":[3.729843952],"iteration":584,"passed_time":0.591941911,"remaining_time":0.4199246035},
{"learn":[3.727223798],"iteration":585,"passed_time":0.592755574,"remaining_time":0.4187727092},
{"learn":[3.725351667],"iteration":586,"passed_time":0.5938256508,"remaining_time":0.4178023744},
{"learn":[3.725026912],"iteration":587,"passed_time":0.5949499561,"remaining_time":0.4168696971},
{"learn":[3.721974565],"iteration":588,"passed_time":0.5961358291,"remaining_time":0.4159793307},
{"learn":[3.720269493],"iteration":589,"passed_time":0.5970771492,"remaining_time":0.4149180189},
{"learn":[3.718907466],"iteration":590,"passed_time":0.597903687,"remaining_time":0.4137776785},
{"learn":[3.715602912],"iteration":591,"passed_time":0.598788694,"remaining_time":0.4126786945},
{"learn":[3.714463059],"iteration":592,"passed_time":0.5995080576,"remaining_time":0.4114667444},
{"learn":[3.710802077],"iteration":593,"passed_time":0.6003144759,"remaining_time":0.4103159549},
{"learn":[3.708032435],"iteration":594,"passed_time":0.6010209093,"remaining_time":0.409098266},
{"learn":[3.703788939],"iteration":595,"passed_time":0.6017601693,"remaining_time":0.4079045443},
{"learn":[3.702500944],"iteration":596,"passed_time":0.6025023153,"remaining_time":0.4067142933},
{"learn":[3.698196925],"iteration":597,"passed_time":0.6032878292,"remaining_time":0.4055546945},
{"learn":[3.69658891],"iteration":598,"passed_time":0.6041712705,"remaining_time":0.4044619023},
{"learn":[3.696124066],"iteration":599,"passed_time":0.6048794544,"remaining_time":0.4032529696},
{"learn":[3.693537052],"iteration":600,"passed_time":0.6056806601,"remaining_time":0.4021074598},
{"learn":[3.691343275],"iteration":601,"passed_time":0.6065499832,"remaining_time":0.4010081284},
{"learn":[3.690973831],"iteration":602,"passed_time":0.60741022,"remaining_time":0.3999035777},
{"learn":[3.686151073],"iteration":603,"passed_time":0.6082199868,"remaining_time":0.3987667463},
{"learn":[3.683921982],"iteration":604,"passed_time":0.609040856,"remaining_time":0.3976382449},
{"learn":[3.679975271],"iteration":605,"passed_time":0.609604549,"remaining_time":0.3963435516},
{"learn":[3.674047638],"iteration":606,"passed_time":0.6103677491,"remaining_time":0.3951804372},
{"learn":[3.673151794],"iteration":607,"passed_time":0.6111639357,"remaining_time":0.3940399059},
{"learn":[3.670953108],"iteration":608,"passed_time":0.6118892324,"remaining_time":0.3928549915},
{"learn":[3.6703947],"iteration":609,"passed_time":0.6126322929,"remaining_time":0.3916829413},
{"learn":[3.668433805],"iteration":610,"passed_time":0.6133496384,"remaining_time":0.3904959236},
{"learn":[3.668304956],"iteration":611,"passed_time":0.6140046566,"remaining_time":0.389270926},
{"learn":[3.667880012],"iteration":612,"passed_time":0.6146891979,"remaining_time":0.3880664268},
{"learn":[3.667282264],"iteration":613,"passed_time":0.6153150122,"remaining_time":0.3868267015},
{"learn":[3.664611483],"iteration":614,"passed_time":0.6160981787,"remaining_time":0.3856874777},
{"learn":[3.662543394],"iteration":615,"passed_time":0.6168647417,"remaining_time":0.3845390598},
{"learn":[3.659041959],"iteration":616,"passed_time":0.6176731229,"remaining_time":0.383417838},
{"learn":[3.656868545],"iteration":617,"passed_time":0.6183335033,"remaining_time":0.382206146},
{"learn":[3.654785614],"iteration":618,"passed_time":0.6190757634,"remaining_time":0.381046633},
{"learn":[3.654566096],"iteration":619,"passed_time":0.619693046,"remaining_time":0.3798118669},
{"learn":[3.651007045],"iteration":620,"passed_time":0.6204187311,"remaining_time":0.3786452481},
{"learn":[3.648921786],"iteration":621,"passed_time":0.6211950457,"remaining_time":0.3775108156},
{"learn":[3.647655706],"iteration":622,"passed_time":0.6219800667,"remaining_time":0.3763828012},
{"learn":[3.647241144],"iteration":623,"passed_time":0.6229242805,"remaining_time":0.37535181},
{"learn":[3.644195689],"iteration":624,"passed_time":0.6239236696,"remaining_time":0.3743542018},
{"learn":[3.642632246],"iteration":625,"passed_time":0.624788275,"remaining_time":0.3732760621},
{"learn":[3.642523322],"iteration":626,"passed_time":0.6254303339,"remaining_time":0.3720662114},
{"learn":[3.641494659],"iteration":627,"passed_time":0.6262529364,"remaining_time":0.3709651152},
{"learn":[3.63976496],"iteration":628,"passed_time":0.6269722328,"remaining_time":0.3698039719},
{"learn":[3.637945652],"iteration":629,"passed_time":0.6278037296,"remaining_time":0.3687101269},
{"learn":[3.636233667],"iteration":630,"passed_time":0.6285287522,"remaining_time":0.3675548488},
{"learn":[3.635304404],"iteration":631,"passed_time":0.6292952941,"remaining_time":0.3664251079},
{"learn":[3.632234951],"iteration":632,"passed_time":0.630129229,"remaining_time":0.3653355878},
{"learn":[3.631630987],"iteration":633,"passed_time":0.6308608483,"remaining_time":0.3641878083},
{"learn":[3.630301009],"iteration":634,"passed_time":0.631539047,"remaining_time":0.3630106333},
{"learn":[3.629077964],"iteration":635,"passed_time":0.6322601966,"remaining_time":0.3618596094},
{"learn":[3.628004522],"iteration":636,"passed_time":0.6329019683,"remaining_time":0.3606647009},
{"learn":[3.625062876],"iteration":637,"passed_time":0.6336792734,"remaining_time":0.3595484278},
{"learn":[3.624917986],"iteration":638,"passed_time":0.6344915003,"remaining_time":0.3584529446},
{"learn":[3.622887087],"iteration":639,"passed_time":0.6353448764,"remaining_time":0.357381493},
{"learn":[3.621220865],"iteration":640,"passed_time":0.6361831587,"remaining_time":0.3563022683},
{"learn":[3.621143844],"iteration":641,"passed_time":0.6369776193,"remaining_time":0.3551993578},
{"learn":[3.620822821],"iteration":642,"passed_time":0.6377466324,"remaining_time":0.354083278},
{"learn":[3.619202826],"iteration":643,"passed_time":0.638471477,"remaining_time":0.35294386},
{"learn":[3.618204882],"iteration":644,"passed_time":0.6391432103,"remaining_time":0.3517764956},
{"learn":[3.614259666],"iteration":645,"passed_time":0.6399283273,"remaining_time":0.3506727985},
{"learn":[3.613415661],"iteration":646,"passed_time":0.6406385953,"remaining_time":0.3495292491},
{"learn":[3.611096773],"iteration":647,"passed_time":0.6413127283,"remaining_time":0.3483674079},
{"learn":[3.610820695],"iteration":648,"passed_time":0.6419945075,"remaining_time":0.3472112051},
{"learn":[3.609290065],"iteration":649,"passed_time":0.642596312,"remaining_time":0.3460133988},
{"learn":[3.60897947],"iteration":650,"passed_time":0.6432686977,"remaining_time":0.3448552619},
{"learn":[3.606570702],"iteration":651,"passed_time":0.6438935871,"remaining_time":0.3436732643},
{"learn":[3.606292637],"iteration":652,"passed_time":0.6445493333,"remaining_time":0.3425093701},
{"learn":[3.602753838],"iteration":653,"passed_time":0.6452644407,"remaining_time":0.341378435},
{"learn":[3.599755869],"iteration":654,"passed_time":0.6460070892,"remaining_time":0.340263276},
{"learn":[3.599509575],"iteration":655,"passed_time":0.6467876452,"remaining_time":0.339169131},
{"learn":[3.595337722],"iteration":656,"passed_time":0.6475193005,"remaining_time":0.3380504111},
{"learn":[3.595168561],"iteration":657,"passed_time":0.6482993261,"remaining_time":0.3369580084},
{"learn":[3.59290559],"iteration":658,"passed_time":0.6491558027,"remaining_time":0.3359061134},
{"learn":[3.592015928],"iteration":659,"passed_time":0.6498476304,"remaining_time":0.3347699914},
{"learn":[3.590680403],"iteration":660,"passed_time":0.650498698,"remaining_time":0.3336143096},
{"learn":[3.590361532],"iteration":661,"passed_time":0.6511216845,"remaining_time":0.3324458148},
{"learn":[3.589069739],"iteration":662,"passed_time":0.651742687,"remaining_time":0.331277957},
{"learn":[3.585010186],"iteration":663,"passed_time":0.6524265283,"remaining_time":0.3301435445},
{"learn":[3.582997552],"iteration":664,"passed_time":0.6531987924,"remaining_time":0.3290550308},
{"learn":[3.582119256],"iteration":665,"passed_time":0.6538653283,"remaining_time":0.3279144439},
{"learn":[3.579019356],"iteration":666,"passed_time":0.654534963,"remaining_time":0.3267768256},
{"learn":[3.57719559],"iteration":667,"passed_time":0.6551241494,"remaining_time":0.3256006252},
{"learn":[3.574050046],"iteration":668,"passed_time":0.6557540198,"remaining_time":0.3244463087},
{"learn":[3.572204518],"iteration":669,"passed_time":0.6563190852,"remaining_time":0.323261639},
{"learn":[3.569508025],"iteration":670,"passed_time":0.6569373623,"remaining_time":0.3221049064},
{"learn":[3.566268704],"iteration":671,"passed_time":0.6574800548,"remaining_time":0.3209128839},
{"learn":[3.562564052],"iteration":672,"passed_time":0.6580459407,"remaining_time":0.3197340603},
{"learn":[3.561173586],"iteration":673,"passed_time":0.6586071339,"remaining_time":0.3185547858},
{"learn":[3.559551904],"iteration":674,"passed_time":0.6591900552,"remaining_time":0.3173878044},
{"learn":[3.558593054],"iteration":675,"passed_time":0.6598481487,"remaining_time":0.3162585802},
{"learn":[3.555647008],"iteration":676,"passed_time":0.6604485263,"remaining_time":0.3151032112},
{"learn":[3.553100059],"iteration":677,"passed_time":0.6610565463,"remaining_time":0.313953109},
{"learn":[3.55085578],"iteration":678,"passed_time":0.6616209312,"remaining_time":0.3127839749},
{"learn":[3.550737965],"iteration":679,"passed_time":0.6621676551,"remaining_time":0.3116083083},
{"learn":[3.549408772],"iteration":680,"passed_time":0.6627404516,"remaining_time":0.310446702},
{"learn":[3.547390589],"iteration":681,"passed_time":0.6633081291,"remaining_time":0.3092844356},
{"learn":[3.54723575],"iteration":682,"passed_time":0.6639201828,"remaining_time":0.3081445065},
{"learn":[3.543988891],"iteration":683,"passed_time":0.6645496236,"remaining_time":0.3070141536},
{"learn":[3.543868508],"iteration":684,"passed_time":0.6651073099,"remaining_time":0.3058522666},
{"learn":[3.542752124],"iteration":685,"passed_time":0.6656780387,"remaining_time":0.304698111},
{"learn":[3.541334315],"iteration":686,"passed_time":0.6663550886,"remaining_time":0.3035940942},
{"learn":[3.540208266],"iteration":687,"passed_time":0.6670867658,"remaining_time":0.3025160915},
{"learn":[3.537730983],"iteration":688,"passed_time":0.6678178279,"remaining_time":0.3014388163},
{"learn":[3.53419867],"iteration":689,"passed_time":0.6684415936,"remaining_time":0.3003143392},
{"learn":[3.532628335],"iteration":690,"passed_time":0.6690870314,"remaining_time":0.2992010025},
{"learn":[3.532204987],"iteration":691,"passed_time":0.669692638,"remaining_time":0.2980712898},
{"learn":[3.530618147],"iteration":692,"passed_time":0.6702666294,"remaining_time":0.296929084},
{"learn":[3.528909306],"iteration":693,"passed_time":0.6708114212,"remaining_time":0.295775641},
{"learn":[3.526700678],"iteration":694,"passed_time":0.6714164454,"remaining_time":0.2946503825},
{"learn":[3.526439574],"iteration":695,"passed_time":0.6719503807,"remaining_time":0.2934955686},
{"learn":[3.525784216],"iteration":696,"passed_time":0.6726555229,"remaining_time":0.2924169633},
{"learn":[3.524112693],"iteration":697,"passed_time":0.6733619788,"remaining_time":0.2913399965},
{"learn":[3.522813541],"iteration":698,"passed_time":0.6741523776,"remaining_time":0.290300237},
{"learn":[3.519148203],"iteration":699,"passed_time":0.6747036524,"remaining_time":0.2891587082},
{"learn":[3.517236747],"iteration":700,"passed_time":0.675366991,"remaining_time":0.2880666623},
{"learn":[3.515603888],"iteration":701,"passed_time":0.6760984446,"remaining_time":0.2870047528},
{"learn":[3.51263524],"iteration":702,"passed_time":0.6767334764,"remaining_time":0.2859030476},
{"learn":[3.51123442],"iteration":703,"passed_time":0.6773899843,"remaining_time":0.2848116979},
{"learn":[3.50828027],"iteration":704,"passed_time":0.6779781682,"remaining_time":0.2836929924},
{"learn":[3.508265537],"iteration":705,"passed_time":0.6784032252,"remaining_time":0.2825078586},
{"learn":[3.506774876],"iteration":706,"passed_time":0.679074294,"remaining_time":0.2814268291},
{"learn":[3.50552068],"iteration":707,"passed_time":0.6796807399,"remaining_time":0.2803203051},
{"learn":[3.501973993],"iteration":708,"passed_time":0.6803913855,"remaining_time":0.2792579594},
{"learn":[3.498880354],"iteration":709,"passed_time":0.6810583678,"remaining_time":0.2781787699},
{"learn":[3.497370959],"iteration":710,"passed_time":0.6816887314,"remaining_time":0.2770858557},
{"learn":[3.496050455],"iteration":711,"passed_time":0.6823327967,"remaining_time":0.275999783},
{"learn":[3.495630067],"iteration":712,"passed_time":0.6828878189,"remaining_time":0.274879108},
{"learn":[3.49550669],"iteration":713,"passed_time":0.6833816223,"remaining_time":0.2737354958},
{"learn":[3.493652375],"iteration":714,"passed_time":0.6840159517,"remaining_time":0.272649715},
{"learn":[3.491915684],"iteration":715,"passed_time":0.684650441,"remaining_time":0.2715652587},
{"learn":[3.490303956],"iteration":716,"passed_time":0.6852493026,"remaining_time":0.2704679953},
{"learn":[3.488363853],"iteration":717,"passed_time":0.6860103262,"remaining_time":0.2694358106},
{"learn":[3.485483936],"iteration":718,"passed_time":0.6867082585,"remaining_time":0.2683797227},
{"learn":[3.483763466],"iteration":719,"passed_time":0.6874735347,"remaining_time":0.2673508191},
{"learn":[3.481642352],"iteration":720,"passed_time":0.6881447956,"remaining_time":0.2662862662},
{"learn":[3.479826119],"iteration":721,"passed_time":0.6887822987,"remaining_time":0.2652098048},
{"learn":[3.478588728],"iteration":722,"passed_time":0.6894411822,"remaining_time":0.2641427489},
{"learn":[3.475390887],"iteration":723,"passed_time":0.6900143451,"remaining_time":0.2630441426},
{"learn":[3.472636852],"iteration":724,"passed_time":0.6906821314,"remaining_time":0.2619828774},
{"learn":[3.47061883],"iteration":725,"passed_time":0.6914583137,"remaining_time":0.260963606},
{"learn":[3.46953149],"iteration":726,"passed_time":0.6919879113,"remaining_time":0.2598524068},
{"learn":[3.467217162],"iteration":727,"passed_time":0.6925262276,"remaining_time":0.2587460631},
{"learn":[3.465686216],"iteration":728,"passed_time":0.6931005886,"remaining_time":0.257654677},
{"learn":[3.462631216],"iteration":729,"passed_time":0.6936338047,"remaining_time":0.2565494894},
{"learn":[3.461451053],"iteration":730,"passed_time":0.6941892861,"remaining_time":0.2554540601},
{"learn":[3.458950469],"iteration":731,"passed_time":0.6949173768,"remaining_time":0.2544233019},
{"learn":[3.458072145],"iteration":732,"passed_time":0.6954734091,"remaining_time":0.2533306961},
{"learn":[3.454364268],"iteration":733,"passed_time":0.6959768016,"remaining_time":0.2522204758},
{"learn":[3.453243406],"iteration":734,"passed_time":0.6967916342,"remaining_time":0.2512241946},
{"learn":[3.453017963],"iteration":735,"passed_time":0.6974188097,"remaining_time":0.2501610948},
{"learn":[3.45201581],"iteration":736,"passed_time":0.6980416646,"remaining_time":0.2490976361},
{"learn":[3.449510107],"iteration":737,"passed_time":0.6985997305,"remaining_time":0.2480123704},
{"learn":[3.447189189],"iteration":738,"passed_time":0.6993059735,"remaining_time":0.2469808648},
{"learn":[3.446423605],"iteration":739,"passed_time":0.7000070672,"remaining_time":0.245948429},
{"learn":[3.445531987],"iteration":740,"passed_time":0.7007396085,"remaining_time":0.2449278793},
{"learn":[3.445328199],"iteration":741,"passed_time":0.7012942382,"remaining_time":0.2438462446},
{"learn":[3.443327544],"iteration":742,"passed_time":0.7018358739,"remaining_time":0.2427615338},
{"learn":[3.441475798],"iteration":743,"passed_time":0.7023730182,"remaining_time":0.2416767374},
{"learn":[3.439046501],"iteration":744,"passed_time":0.7031707301,"remaining_time":0.2406825989},
{"learn":[3.435899469],"iteration":745,"passed_time":0.7038332098,"remaining_time":0.2396429427},
{"learn":[3.433988352],"iteration":746,"passed_time":0.7044515005,"remaining_time":0.2385893302},
{"learn":[3.433413263],"iteration":747,"passed_time":0.7051294856,"remaining_time":0.2375569925},
{"learn":[3.429944699],"iteration":748,"passed_time":0.7057795976,"remaining_time":0.2365162604},
{"learn":[3.429291634],"iteration":749,"passed_time":0.7063307741,"remaining_time":0.2354435914},
{"learn":[3.429175603],"iteration":750,"passed_time":0.7069622157,"remaining_time":0.2343989237},
{"learn":[3.428780323],"iteration":751,"passed_time":0.7075208073,"remaining_time":0.2333313301},
{"learn":[3.423893341],"iteration":752,"passed_time":0.7081952266,"remaining_time":0.2323030823},
{"learn":[3.421024316],"iteration":753,"passed_time":0.7088778503,"remaining_time":0.2312784498},
{"learn":[3.420969872],"iteration":754,"passed_time":0.7095917569,"remaining_time":0.2302648748},
{"learn":[3.419544785],"iteration":755,"passed_time":0.7101982163,"remaining_time":0.2292174137},
{"learn":[3.417057977],"iteration":756,"passed_time":0.7109434401,"remaining_time":0.2282156618},
{"learn":[3.415160245],"iteration":757,"passed_time":0.7115738054,"remaining_time":0.2271779167},
{"learn":[3.412854597],"iteration":758,"passed_time":0.7123102036,"remaining_time":0.2261749131},
{"learn":[3.410926347],"iteration":759,"passed_time":0.7128738181,"remaining_time":0.2251180478},
{"learn":[3.408963843],"iteration":760,"passed_time":0.7135739921,"remaining_time":0.2241053668},
{"learn":[3.407629634],"iteration":761,"passed_time":0.7142351662,"remaining_time":0.2230813249},
{"learn":[3.404384724],"iteration":762,"passed_time":0.7149351814,"remaining_time":0.2220702988},
{"learn":[3.403041656],"iteration":763,"passed_time":0.7155285071,"remaining_time":0.2210271305},
{"learn":[3.401101731],"iteration":764,"passed_time":0.7161939833,"remaining_time":0.2200073021},
{"learn":[3.400890668],"iteration":765,"passed_time":0.7169805232,"remaining_time":0.2190253818},
{"learn":[3.399289941],"iteration":766,"passed_time":0.7177664798,"remaining_time":0.2180437937},
{"learn":[3.399202366],"iteration":767,"passed_time":0.7183979511,"remaining_time":0.2170160477},
{"learn":[3.397447845],"iteration":768,"passed_time":0.7190385339,"remaining_time":0.2159920693},
{"learn":[3.394655341],"iteration":769,"passed_time":0.7196238953,"remaining_time":0.2149525921},
{"learn":[3.393228229],"iteration":770,"passed_time":0.7202017056,"remaining_time":0.21391205},
{"learn":[3.389691197],"iteration":771,"passed_time":0.7207233189,"remaining_time":0.2128561097},
{"learn":[3.389626772],"iteration":772,"passed_time":0.7212202003,"remaining_time":0.2117942891},
{"learn":[3.388480222],"iteration":773,"passed_time":0.7217637309,"remaining_time":0.2107475493},
{"learn":[3.388215066],"iteration":774,"passed_time":0.7222807679,"remaining_time":0.2096944165},
{"learn":[3.386324358],"iteration":775,"passed_time":0.7228243197,"remaining_time":0.2086503191},
{"learn":[3.383913061],"iteration":776,"passed_time":0.7233603887,"remaining_time":0.2076053625},
{"learn":[3.382839768],"iteration":777,"passed_time":0.7238855465,"remaining_time":0.2065586007},
{"learn":[3.381961844],"iteration":778,"passed_time":0.7244262545,"remaining_time":0.2055175895},
{"learn":[3.381521703],"iteration":779,"passed_time":0.7249364081,"remaining_time":0.2044692433},
{"learn":[3.380918963],"iteration":780,"passed_time":0.7254575638,"remaining_time":0.2034253604},
{"learn":[3.377139006],"iteration":781,"passed_time":0.7259886666,"remaining_time":0.2023855874},
{"learn":[3.376004372],"iteration":782,"passed_time":0.7265303991,"remaining_time":0.2013500595},
{"learn":[3.373826468],"iteration":783,"passed_time":0.7270410259,"remaining_time":0.2003072214},
{"learn":[3.373546786],"iteration":784,"passed_time":0.7275696947,"remaining_time":0.1992706807},
{"learn":[3.372109181],"iteration":785,"passed_time":0.7281180314,"remaining_time":0.1982407872},
{"learn":[3.370764924],"iteration":786,"passed_time":0.7286588042,"remaining_time":0.1972100703},
{"learn":[3.367833107],"iteration":787,"passed_time":0.7291850165,"remaining_time":0.1961766796},
{"learn":[3.36450404],"iteration":788,"passed_time":0.7296977058,"remaining_time":0.1951409581},
{"learn":[3.361794558],"iteration":789,"passed_time":0.7303435956,"remaining_time":0.1941419684},
{"learn":[3.356880529],"iteration":790,"passed_time":0.7312983614,"remaining_time":0.1932254836},
{"learn":[3.353843509],"iteration":791,"passed_time":0.7320001438,"remaining_time":0.192242462},
{"learn":[3.353640253],"iteration":792,"passed_time":0.7325982678,"remaining_time":0.1912330913},
{"learn":[3.353055088],"iteration":793,"passed_time":0.7331582926,"remaining_time":0.1902148719},
{"learn":[3.351415617],"iteration":794,"passed_time":0.7337163205,"remaining_time":0.1891972902},
{"learn":[3.349169061],"iteration":795,"passed_time":0.7342238268,"remaining_time":0.1881679154},
{"learn":[3.346211014],"iteration":796,"passed_time":0.7348128771,"remaining_time":0.1871606199},
{"learn":[3.344560452],"iteration":797,"passed_time":0.7353992682,"remaining_time":0.1861536995},
{"learn":[3.344445461],"iteration":798,"passed_time":0.7359399266,"remaining_time":0.185136327},
{"learn":[3.342608898],"iteration":799,"passed_time":0.7364625019,"remaining_time":0.1841156255},
{"learn":[3.339572899],"iteration":800,"passed_time":0.736995088,"remaining_time":0.1830986548},
{"learn":[3.339309302],"iteration":801,"passed_time":0.7374687381,"remaining_time":0.1820683418},
{"learn":[3.33698088],"iteration":802,"passed_time":0.7379656068,"remaining_time":0.1810451115},
{"learn":[3.334746342],"iteration":803,"passed_time":0.738509715,"remaining_time":0.1800347066},
{"learn":[3.332048511],"iteration":804,"passed_time":0.7390399582,"remaining_time":0.1790221017},
{"learn":[3.331932544],"iteration":805,"passed_time":0.7395632695,"remaining_time":0.1780090252},
{"learn":[3.330541133],"iteration":806,"passed_time":0.7400585505,"remaining_time":0.1769904588},
{"learn":[3.329124989],"iteration":807,"passed_time":0.7406100782,"remaining_time":0.1759865532},
{"learn":[3.32583918],"iteration":808,"passed_time":0.7411885233,"remaining_time":0.1749901211},
{"learn":[3.325287299],"iteration":809,"passed_time":0.7418283277,"remaining_time":0.1740091139},
{"learn":[3.322745162],"iteration":810,"passed_time":0.742395962,"remaining_time":0.1730121292},
{"learn":[3.319733662],"iteration":811,"passed_time":0.7428994129,"remaining_time":0.1720013419},
{"learn":[3.318080007],"iteration":812,"passed_time":0.7434307514,"remaining_time":0.1709982171},
{"learn":[3.317179538],"iteration":813,"passed_time":0.7440966696,"remaining_time":0.1700270031},
{"learn":[3.315685949],"iteration":814,"passed_time":0.7446452419,"remaining_time":0.1690299015},
{"learn":[3.314944576],"iteration":815,"passed_time":0.7451848163,"remaining_time":0.1680318703},
{"learn":[3.312369052],"iteration":816,"passed_time":0.74574639,"remaining_time":0.1670398891},
{"learn":[3.312321621],"iteration":817,"passed_time":0.7461412822,"remaining_time":0.1660118745},
{"learn":[3.309465776],"iteration":818,"passed_time":0.7467061784,"remaining_time":0.1650229771},
{"learn":[3.308307377],"iteration":819,"passed_time":0.7472425174,"remaining_time":0.1640288453},
{"learn":[3.308076804],"iteration":820,"passed_time":0.7477615782,"remaining_time":0.1630320615},
{"learn":[3.305643326],"iteration":821,"passed_time":0.7482794233,"remaining_time":0.1620361768},
{"learn":[3.304154814],"iteration":822,"passed_time":0.7487775764,"remaining_time":0.1610372187},
{"learn":[3.303076321],"iteration":823,"passed_time":0.7493104157,"remaining_time":0.1600468849},
{"learn":[3.301746372],"iteration":824,"passed_time":0.7498300261,"remaining_time":0.159054854},
{"learn":[3.301345455],"iteration":825,"passed_time":0.7503244479,"remaining_time":0.1580586609},
{"learn":[3.299181039],"iteration":826,"passed_time":0.7508153799,"remaining_time":0.1570629513},
{"learn":[3.297989357],"iteration":827,"passed_time":0.7513664575,"remaining_time":0.1560809549},
{"learn":[3.294775182],"iteration":828,"passed_time":0.7518618514,"remaining_time":0.1550885122},
{"learn":[3.293840636],"iteration":829,"passed_time":0.752372107,"remaining_time":0.1541003111},
{"learn":[3.289279397],"iteration":830,"passed_time":0.7529201637,"remaining_time":0.1531209478},
{"learn":[3.286204979],"iteration":831,"passed_time":0.7534756311,"remaining_time":0.1521441178},
{"learn":[3.284833593],"iteration":832,"passed_time":0.754003167,"remaining_time":0.1511626997},
{"learn":[3.283519914],"iteration":833,"passed_time":0.7545466927,"remaining_time":0.1501855527},
{"learn":[3.282853026],"iteration":834,"passed_time":0.7550839646,"remaining_time":0.1492082086},
{"learn":[3.281944673],"iteration":835,"passed_time":0.7556940906,"remaining_time":0.1482462092},
{"learn":[3.279764865],"iteration":836,"passed_time":0.7563454239,"remaining_time":0.1472930754},
{"learn":[3.277468839],"iteration":837,"passed_time":0.7568919605,"remaining_time":0.1463204029},
{"learn":[3.277124974],"iteration":838,"passed_time":0.7574071863,"remaining_time":0.1453427378},
{"learn":[3.275636037],"iteration":839,"passed_time":0.7582277659,"remaining_time":0.1444243364},
{"learn":[3.274413635],"iteration":840,"passed_time":0.7589521745,"remaining_time":0.1434879854},
{"learn":[3.272636087],"iteration":841,"passed_time":0.7595521437,"remaining_time":0.1425287871},
{"learn":[3.269644466],"iteration":842,"passed_time":0.76012056,"remaining_time":0.1415645646},
{"learn":[3.26852083],"iteration":843,"passed_time":0.7607427145,"remaining_time":0.1406112126},
{"learn":[3.267820927],"iteration":844,"passed_time":0.7613351166,"remaining_time":0.1396531871},
{"learn":[3.267331099],"iteration":845,"passed_time":0.7619090952,"remaining_time":0.1386926722},
{"learn":[3.267231014],"iteration":846,"passed_time":0.7624786163,"remaining_time":0.1377322648},
{"learn":[3.267158695],"iteration":847,"passed_time":0.7630889315,"remaining_time":0.1367800915},
{"learn":[3.264718705],"iteration":848,"passed_time":0.7637229253,"remaining_time":0.1358329349},
{"learn":[3.261678512],"iteration":849,"passed_time":0.7643228701,"remaining_time":0.1348805065},
{"learn":[3.261368381],"iteration":850,"passed_time":0.7648889311,"remaining_time":0.1339229738},
{"learn":[3.260128799],"iteration":851,"passed_time":0.7655383779,"remaining_time":0.132980845},
{"learn":[3.258972952],"iteration":852,"passed_time":0.7661253138,"remaining_time":0.1320286297},
{"learn":[3.258724846],"iteration":853,"passed_time":0.7666541621,"remaining_time":0.1310673392},
{"learn":[3.25686724],"iteration":854,"passed_time":0.7672156254,"remaining_time":0.1301125914},
{"learn":[3.255750259],"iteration":855,"passed_time":0.7677679583,"remaining_time":0.1291572266},
{"learn":[3.254915866],"iteration":856,"passed_time":0.7683274502,"remaining_time":0.1282039969},
{"learn":[3.254348625],"iteration":857,"passed_time":0.7688467546,"remaining_time":0.127245034},
{"learn":[3.253408514],"iteration":858,"passed_time":0.7694931225,"remaining_time":0.1263079514},
{"learn":[3.253291714],"iteration":859,"passed_time":0.7700753182,"remaining_time":0.1253610983},
{"learn":[3.250186342],"iteration":860,"passed_time":0.7707590839,"remaining_time":0.1244314897},
{"learn":[3.249141318],"iteration":861,"passed_time":0.7714421108,"remaining_time":0.1235023333},
{"learn":[3.246300388],"iteration":862,"passed_time":0.7720279866,"remaining_time":0.1225583246},
{"learn":[3.245205135],"iteration":863,"passed_time":0.7726165194,"remaining_time":0.1216155632},
{"learn":[3.244403535],"iteration":864,"passed_time":0.7734212228,"remaining_time":0.1207073585},
{"learn":[3.244211781],"iteration":865,"passed_time":0.7741894675,"remaining_time":0.1197937513},
{"learn":[3.242286347],"iteration":866,"passed_time":0.775022492,"remaining_time":0.1188904169},
{"learn":[3.239606746],"iteration":867,"passed_time":0.7757836288,"remaining_time":0.1179763122},
{"learn":[3.236773361],"iteration":868,"passed_time":0.7765039268,"remaining_time":0.1170564032},
{"learn":[3.234552446],"iteration":869,"passed_time":0.7772363785,"remaining_time":0.1161387692},
{"learn":[3.233724647],"iteration":870,"passed_time":0.7778310131,"remaining_time":0.1152011489},
{"learn":[3.230851485],"iteration":871,"passed_time":0.7784502695,"remaining_time":0.1142679295},
{"learn":[3.227728941],"iteration":872,"passed_time":0.7790253209,"remaining_time":0.1133289986},
{"learn":[3.225787575],"iteration":873,"passed_time":0.7796390762,"remaining_time":0.1123964801},
{"learn":[3.222797487],"iteration":874,"passed_time":0.7803322811,"remaining_time":0.1114760402},
{"learn":[3.22137014],"iteration":875,"passed_time":0.7809515923,"remaining_time":0.1105456592},
{"learn":[3.219701963],"iteration":876,"passed_time":0.7815134364,"remaining_time":0.1096079278},
{"learn":[3.21783327],"iteration":877,"passed_time":0.7822323211,"remaining_time":0.1086928738},
{"learn":[3.217713355],"iteration":878,"passed_time":0.7828384038,"remaining_time":0.1077627382},
{"learn":[3.217666091],"iteration":879,"passed_time":0.7834173781,"remaining_time":0.1068296425},
{"learn":[3.214962005],"iteration":880,"passed_time":0.7840326183,"remaining_time":0.1059022492},
{"learn":[3.214081828],"iteration":881,"passed_time":0.784625086,"remaining_time":0.1049725172},
{"learn":[3.213358337],"iteration":882,"passed_time":0.7852102514,"remaining_time":0.1040425814},
{"learn":[3.210850401],"iteration":883,"passed_time":0.7859132959,"remaining_time":0.103128894},
{"learn":[3.207810328],"iteration":884,"passed_time":0.786554162,"remaining_time":0.102207603},
{"learn":[3.204935073],"iteration":885,"passed_time":0.7872475713,"remaining_time":0.1012937056},
{"learn":[3.20280198],"iteration":886,"passed_time":0.7878882481,"remaining_time":0.1003735874},
{"learn":[3.200663495],"iteration":887,"passed_time":0.7885384749,"remaining_time":0.09945530314},
{"learn":[3.197301669],"iteration":888,"passed_time":0.7892276993,"remaining_time":0.09854249114},
{"learn":[3.195666943],"iteration":889,"passed_time":0.7898353276,"remaining_time":0.09762009667},
{"learn":[3.193886506],"iteration":890,"passed_time":0.7905695898,"remaining_time":0.09671390043},
{"learn":[3.190601248],"iteration":891,"passed_time":0.7911790069,"remaining_time":0.09579297393},
{"learn":[3.188983797],"iteration":892,"passed_time":0.7918632495,"remaining_time":0.09488171075},
{"learn":[3.187365749],"iteration":893,"passed_time":0.792454914,"remaining_time":0.09395997861},
{"learn":[3.186160771],"iteration":894,"passed_time":0.7930261388,"remaining_time":0.09303658612},
{"learn":[3.185358981],"iteration":895,"passed_time":0.7936112534,"remaining_time":0.09211559191},
{"learn":[3.183832164],"iteration":896,"passed_time":0.7941746999,"remaining_time":0.09119285852},
{"learn":[3.183106966],"iteration":897,"passed_time":0.7948027683,"remaining_time":0.09027826544},
{"learn":[3.182838152],"iteration":898,"passed_time":0.7954941399,"remaining_time":0.08937142172},
{"learn":[3.180835453],"iteration":899,"passed_time":0.7961730055,"remaining_time":0.08846366727},
{"learn":[3.179957348],"iteration":900,"passed_time":0.796801799,"remaining_time":0.08755091909},
{"learn":[3.179752966],"iteration":901,"passed_time":0.7974493265,"remaining_time":0.08664083592},
{"learn":[3.178851983],"iteration":902,"passed_time":0.7981660508,"remaining_time":0.08573876736},
{"learn":[3.176748586],"iteration":903,"passed_time":0.7987852871,"remaining_time":0.08482675615},
{"learn":[3.172960988],"iteration":904,"passed_time":0.7994957915,"remaining_time":0.08392497259},
{"learn":[3.172794225],"iteration":905,"passed_time":0.8001954403,"remaining_time":0.08302248498},
{"learn":[3.169996507],"iteration":906,"passed_time":0.8007815226,"remaining_time":0.0821088},
{"learn":[3.16813015],"iteration":907,"passed_time":0.8015396317,"remaining_time":0.08121326665},
{"learn":[3.166920871],"iteration":908,"passed_time":0.802227854,"remaining_time":0.08031103929},
{"learn":[3.16531606],"iteration":909,"passed_time":0.8029901637,"remaining_time":0.0794166096},
{"learn":[3.162035247],"iteration":910,"passed_time":0.8036389352,"remaining_time":0.07851137787},
{"learn":[3.16189467],"iteration":911,"passed_time":0.804217072,"remaining_time":0.07759989291},
{"learn":[3.161008416],"iteration":912,"passed_time":0.8048719749,"remaining_time":0.07669645325},
{"learn":[3.160560787],"iteration":913,"passed_time":0.8055361975,"remaining_time":0.07579443434},
{"learn":[3.160416261],"iteration":914,"passed_time":0.806177664,"remaining_time":0.07489082124},
{"learn":[3.15844291],"iteration":915,"passed_time":0.8067686928,"remaining_time":0.07398315523},
{"learn":[3.155040501],"iteration":916,"passed_time":0.8073756235,"remaining_time":0.07307761914},
{"learn":[3.154937548],"iteration":917,"passed_time":0.8079674639,"remaining_time":0.07217138567},
{"learn":[3.153721161],"iteration":918,"passed_time":0.8085549974,"remaining_time":0.07126545679},
{"learn":[3.153170511],"iteration":919,"passed_time":0.809229228,"remaining_time":0.07036775896},
{"learn":[3.153113601],"iteration":920,"passed_time":0.8098944118,"remaining_time":0.06946977039},
{"learn":[3.150607379],"iteration":921,"passed_time":0.8105339918,"remaining_time":0.06857012078},
{"learn":[3.148408359],"iteration":922,"passed_time":0.8111587488,"remaining_time":0.06766979811},
{"learn":[3.147495728],"iteration":923,"passed_time":0.8118444838,"remaining_time":0.06677508741},
{"learn":[3.146946235],"iteration":924,"passed_time":0.812509276,"remaining_time":0.06587913048},
{"learn":[3.14472738],"iteration":925,"passed_time":0.8131966239,"remaining_time":0.06498547534},
{"learn":[3.144469477],"iteration":926,"passed_time":0.8139821561,"remaining_time":0.06409999719},
{"learn":[3.142975516],"iteration":927,"passed_time":0.8148918489,"remaining_time":0.06322436758},
{"learn":[3.14079113],"iteration":928,"passed_time":0.8157330413,"remaining_time":0.06234342942},
{"learn":[3.138173032],"iteration":929,"passed_time":0.8163961338,"remaining_time":0.06144917136},
{"learn":[3.136352813],"iteration":930,"passed_time":0.8170152966,"remaining_time":0.0605521541},
{"learn":[3.133735004],"iteration":931,"passed_time":0.8177189291,"remaining_time":0.05966189612},
{"learn":[3.1319496],"iteration":932,"passed_time":0.8183814348,"remaining_time":0.05876908482},
{"learn":[3.129865343],"iteration":933,"passed_time":0.8189501788,"remaining_time":0.05787014111},
{"learn":[3.129830206],"iteration":934,"passed_time":0.8194382067,"remaining_time":0.05696629244},
{"learn":[3.126676562],"iteration":935,"passed_time":0.8199932501,"remaining_time":0.05606791454},
{"learn":[3.12645665],"iteration":936,"passed_time":0.8205765474,"remaining_time":0.05517216914},
{"learn":[3.126378007],"iteration":937,"passed_time":0.821276315,"remaining_time":0.05428478841},
{"learn":[3.124621914],"iteration":938,"passed_time":0.8218979494,"remaining_time":0.05339273154},
{"learn":[3.123379018],"iteration":939,"passed_time":0.8224733129,"remaining_time":0.05249829657},
{"learn":[3.123332451],"iteration":940,"passed_time":0.8230204743,"remaining_time":0.0516027715},
{"learn":[3.122432444],"iteration":941,"passed_time":0.8236638585,"remaining_time":0.05071391061},
{"learn":[3.121889006],"iteration":942,"passed_time":0.8242963454,"remaining_time":0.04982491165},
{"learn":[3.121070914],"iteration":943,"passed_time":0.824872908,"remaining_time":0.04893313861},
{"learn":[3.118444705],"iteration":944,"passed_time":0.8255146873,"remaining_time":0.04804582836},
{"learn":[3.116820458],"iteration":945,"passed_time":0.8262509727,"remaining_time":0.04716443185},
{"learn":[3.114971041],"iteration":946,"passed_time":0.8269048777,"remaining_time":0.04627873127},
{"learn":[3.114685138],"iteration":947,"passed_time":0.8275788554,"remaining_time":0.04539462076},
{"learn":[3.113399363],"iteration":948,"passed_time":0.8280972462,"remaining_time":0.04450259173},
{"learn":[3.110575399],"iteration":949,"passed_time":0.8286160329,"remaining_time":0.04361137015},
{"learn":[3.110466553],"iteration":950,"passed_time":0.82925293,"remaining_time":0.04272701742},
{"learn":[3.108691641],"iteration":951,"passed_time":0.8299549737,"remaining_time":0.04184646926},
{"learn":[3.107898017],"iteration":952,"passed_time":0.8307063861,"remaining_time":0.04096873048},
{"learn":[3.105551729],"iteration":953,"passed_time":0.8313039024,"remaining_time":0.04008383597},
{"learn":[3.104824945],"iteration":954,"passed_time":0.8319709247,"remaining_time":0.03920281844},
{"learn":[3.103186704],"iteration":955,"passed_time":0.8326086822,"remaining_time":0.03832090169},
{"learn":[3.102330655],"iteration":956,"passed_time":0.8331760265,"remaining_time":0.03743633139},
{"learn":[3.102291298],"iteration":957,"passed_time":0.8337070385,"remaining_time":0.0365508305},
{"learn":[3.100363529],"iteration":958,"passed_time":0.8342965861,"remaining_time":0.03566857146},
{"learn":[3.097871596],"iteration":959,"passed_time":0.8350182378,"remaining_time":0.03479242657},
{"learn":[3.097372213],"iteration":960,"passed_time":0.8356217103,"remaining_time":0.03391180718},
{"learn":[3.095981813],"iteration":961,"passed_time":0.8361778357,"remaining_time":0.03302989372},
{"learn":[3.095347452],"iteration":962,"passed_time":0.8368246296,"remaining_time":0.03215214049},
{"learn":[3.094728409],"iteration":963,"passed_time":0.8374379841,"remaining_time":0.03127361766},
{"learn":[3.094118537],"iteration":964,"passed_time":0.8380001126,"remaining_time":0.03039378647},
{"learn":[3.093793695],"iteration":965,"passed_time":0.8385961984,"remaining_time":0.02951580823},
{"learn":[3.092581602],"iteration":966,"passed_time":0.8391215227,"remaining_time":0.02863599819},
{"learn":[3.091694202],"iteration":967,"passed_time":0.839646254,"remaining_time":0.02775690096},
{"learn":[3.090298312],"iteration":968,"passed_time":0.840274986,"remaining_time":0.0268818623},
{"learn":[3.090020107],"iteration":969,"passed_time":0.8409333535,"remaining_time":0.02600824805},
{"learn":[3.088949869],"iteration":970,"passed_time":0.8416427883,"remaining_time":0.02513660233},
{"learn":[3.086700204],"iteration":971,"passed_time":0.8424113122,"remaining_time":0.02426699253},
{"learn":[3.086584317],"iteration":972,"passed_time":0.8430482493,"remaining_time":0.02339393909},
{"learn":[3.084850742],"iteration":973,"passed_time":0.8436847699,"remaining_time":0.02252135936},
{"learn":[3.084239948],"iteration":974,"passed_time":0.8443733595,"remaining_time":0.02165059896},
{"learn":[3.082561673],"iteration":975,"passed_time":0.8450872524,"remaining_time":0.02078083408},
{"learn":[3.07991814],"iteration":976,"passed_time":0.8457262984,"remaining_time":0.01990962627},
{"learn":[3.079350277],"iteration":977,"passed_time":0.8463356488,"remaining_time":0.01903822523},
{"learn":[3.077637462],"iteration":978,"passed_time":0.8470228062,"remaining_time":0.01816902853},
{"learn":[3.076733301],"iteration":979,"passed_time":0.8477084433,"remaining_time":0.01730017231},
{"learn":[3.07594065],"iteration":980,"passed_time":0.8483718074,"remaining_time":0.01643125825},
{"learn":[3.072594655],"iteration":981,"passed_time":0.8491099437,"remaining_time":0.01556413339},
{"learn":[3.071977674],"iteration":982,"passed_time":0.8497908721,"remaining_time":0.01469628161},
{"learn":[3.069532634],"iteration":983,"passed_time":0.8504213746,"remaining_time":0.01382798983},
{"learn":[3.068870784],"iteration":984,"passed_time":0.8510567076,"remaining_time":0.01296025443},
{"learn":[3.068801463],"iteration":985,"passed_time":0.851768498,"remaining_time":0.01209407604},
{"learn":[3.067433249],"iteration":986,"passed_time":0.8523392153,"remaining_time":0.01122635238},
{"learn":[3.065611456],"iteration":987,"passed_time":0.8529514061,"remaining_time":0.01035973368},
{"learn":[3.063039162],"iteration":988,"passed_time":0.8535487068,"remaining_time":0.009493463878},
{"learn":[3.06177873],"iteration":989,"passed_time":0.8541098549,"remaining_time":0.008627372271},
{"learn":[3.061689148],"iteration":990,"passed_time":0.8547535122,"remaining_time":0.007762645419},
{"learn":[3.058984039],"iteration":991,"passed_time":0.8553718909,"remaining_time":0.006898160411},
{"learn":[3.057492984],"iteration":992,"passed_time":0.8559897725,"remaining_time":0.00603416758},
{"learn":[3.057290731],"iteration":993,"passed_time":0.8565600125,"remaining_time":0.005170382369},
{"learn":[3.056068348],"iteration":994,"passed_time":0.857094601,"remaining_time":0.004307008045},
{"learn":[3.054987307],"iteration":995,"passed_time":0.8577290144,"remaining_time":0.003444694837},
{"learn":[3.054200234],"iteration":996,"passed_time":0.8583511877,"remaining_time":0.002582801969},
{"learn":[3.052732869],"iteration":997,"passed_time":0.8591231942,"remaining_time":0.001721689768},
{"learn":[3.051787862],"iteration":998,"passed_time":0.8596925461,"remaining_time":0.0008605530992},
{"learn":[3.051366222],"iteration":999,"passed_time":0.8602811725,"remaining_time":0}
]}